DigitalCircuit/greatking/1.v
`timescale 1ns / 1ps
//////////////////////////////////////////////////////////////////////////////////
// Company: 
// Engineer: 
// 
// Create Date: 2017/11/02 01:05:16
// Design Name: 
// Module Name: mealyfsm
// Project Name: 
// Target Devices: 
// Tool Versions: 
// Description: 
// 
// Dependencies: 
// 
// Revision:
// Revision 0.01 - File Created
// Additional Comments:
// 
//////////////////////////////////////////////////////////////////////////////////


module mealyfsm(clk,rst,a,b,out);
     input     clk;
     input     rst;
     input     a;
     input     b;
     output    [3:0] out;
     reg [3:0] currentstate,nextstate;
     reg [3:0] out;
     parameter S0 = 4'b0000;
     parameter S1 = 4'b0001;
     parameter S2 = 4'b0010;
     parameter S3 = 4'b0011;
     parameter S4 = 4'b0100;
     parameter S5 = 4'b0101;
always@(posedge clk or negedge rst)
    if(!rst)
      currentstate <= S0;
    else
      currentstate <= nextstate;
always@(currentstate or a or rst)
    if(!rst)
      nextstate = S0;
    else 
      case(currentstate)
        S0: if (a==1) nextstate = (b == 1)? S1 : S5;
                      else 
                      begin
                      nextstate = S0;
                      $display("Error404:Undefined Step!");
                      end
        S1: if (a==1&&b==0)nextstate = S4;
                           else if (a==0&&b==1) nextstate = S3;
                           else 
                           begin
                           nextstate = S1;
                           $display("Error404:Undefined Step!");
                           end
        S2: if (a==0&&b==0)nextstate = S1;
                           else if (a==1&&b==0) nextstate = S5;
                           else 
                           begin
                           nextstate = S2;
                           $display("Error404:Undefined Step!");
                           end
        S3: if (a==0&&b==0)nextstate = S2;
                           else if (a==1&&b==0) nextstate = S4;
                           else 
                           begin
                           nextstate = S3;
                           $display("Error404:Undefined Step!");
                           end
        S4: if (a==1&&b==0)nextstate = S3;
                           else if (a==0&&b==1) nextstate = S5;
                           else 
                           begin
                           nextstate = S4;
                           $display("Error404:Undefined Step!");
                           end
        S5: if (a==0&&b==0)nextstate = S5;
                           else if (a==1&&b==0) nextstate = S1;
                           else 
                           begin
                           nextstate = S5;
                           $display("Error404:Undefined Step!");
                           end
        default:nextstate = S0;
      endcase 
always @(currentstate)
begin
  case(currentstate)
      S0:out = 4'b0000;
      S1:out = 4'b0001;
      S2:out = 4'b0010;
      S3:out = 4'b0011;
      S4:out = 4'b0100;
      S5:out = 4'b0101;
      default:out = 4'b0000;
  endcase
end
endmodule

DigitalCircuit/状态机基础/greatking/2.v
`timescale 1ns / 1ps
//////////////////////////////////////////////////////////////////////////////////
// Company: 
// Engineer: 
// 
// Create Date: 2017/11/02 00:42:11
// Design Name: 
// Module Name: text
// Project Name: 
// Target Devices: 
// Tool Versions: 
// Description: 
// 
// Dependencies: 
// 
// Revision:
// Revision 0.01 - File Created
// Additional Comments:
// 
//////////////////////////////////////////////////////////////////////////////////
module tb_fsm;
  reg clk,rst;
  reg  a,b;
  wire [3:0] out;
  mealyfsm 
    fsm(.clk(clk),.rst(rst),.a(a),.b(b),.out(out));
    initial
    begin
$dumpfile("out.vcd");  
   $dumpvars(0,tb_fsm);
      a = 0;
      b = 0;
      clk = 0;
      rst = 1;
    end
    
    initial
    begin
      repeat (100) #7 clk=~clk;
      end
    
    initial
      repeat (34) 
      begin
      #23 a=~a;
      #23 b=~b;
      end
    
    initial
      begin
        #31 rst = 1;
        #23 rst = 0;
              $display("currentstate:%d nextstate:%d step:%d %d",fsm.currentstate,fsm.nextstate,a,b); 

      end
      
  /*initial
    begin
      clk = 0;
      rst = 1;
      #5 rst = 0;
      #3 rst = 1;
      #20 a = 0;b = 0;
      #20 b = 1;
      #20 a = 0;
      #20 b = 0;
      $display("currentstate:%d nextstate:%d step:%d %d",currentstate,nextstate,a,b);
      #10000;
      $finish;
    end;
  always #50 clk = ~clk;
$display("currentstate:%d nextstate:%d step:%d %d",currentstate,nextstate,a,b);*/
endmodule

DigitalCircuit/greatking/out.vcd
$date
	Thu Nov 02 20:32:51 2017
$end
$version
	Icarus Verilog
$end
$timescale
	1ps
$end
$scope module tb_fsm $end
$var wire 4 ! out [3:0] $end
$var reg 1 " a $end
$var reg 1 # b $end
$var reg 1 $ clk $end
$var reg 1 % rst $end
$scope module fsm $end
$var wire 1 " a $end
$var wire 1 # b $end
$var wire 1 $ clk $end
$var wire 1 % rst $end
$var reg 4 & currentstate [3:0] $end
$var reg 4 ' nextstate [3:0] $end
$var reg 4 ( out [3:0] $end
$upscope $end
$upscope $end
$enddefinitions $end
#0
$dumpvars
bx (
b0 '
bx &
1%
0$
0#
0"
bx !
$end
#7000
b0 !
b0 (
b0 &
1$
#14000
0$
#21000
1$
#23000
b101 '
1"
#28000
0$
#35000
b101 !
b101 (
b1 '
b101 &
1$
#42000
0$
#46000
1#
#49000
b1 !
b1 (
b1 &
1$
#54000
b0 !
b0 (
b0 &
b0 '
0%
#56000
0$
#63000
1$
#69000
0"
#70000
0$
#77000
1$
#84000
0$
#91000
1$
#92000
0#
#98000
0$
#105000
1$
#112000
0$
#115000
1"
#119000
1$
#126000
0$
#133000
1$
#138000
1#
#140000
0$
#147000
1$
#154000
0$
#161000
1$
0"
#168000
0$
#175000
1$
#182000
0$
#184000
0#
#189000
1$
#196000
0$
#203000
1$
#207000
1"
#210000
0$
#217000
1$
#224000
0$
#230000
1#
#231000
1$
#238000
0$
#245000
1$
#252000
0$
#253000
0"
#259000
1$
#266000
0$
#273000
1$
#276000
0#
#280000
0$
#287000
1$
#294000
0$
#299000
1"
#301000
1$
#308000
0$
#315000
1$
#322000
0$
1#
#329000
1$
#336000
0$
#343000
1$
#345000
0"
#350000
0$
#357000
1$
#364000
0$
#368000
0#
#371000
1$
#378000
0$
#385000
1$
#391000
1"
#392000
0$
#399000
1$
#406000
0$
#413000
1$
#414000
1#
#420000
0$
#427000
1$
#434000
0$
#437000
0"
#441000
1$
#448000
0$
#455000
1$
#460000
0#
#462000
0$
#469000
1$
#476000
0$
#483000
1$
1"
#490000
0$
#497000
1$
#504000
0$
#506000
1#
#511000
1$
#518000
0$
#525000
1$
#529000
0"
#532000
0$
#539000
1$
#546000
0$
#552000
0#
#553000
1$
#560000
0$
#567000
1$
#574000
0$
#575000
1"
#581000
1$
#588000
0$
#595000
1$
#598000
1#
#602000
0$
#609000
1$
#616000
0$
#621000
0"
#623000
1$
#630000
0$
#637000
1$
#644000
0$
0#
#651000
1$
#658000
0$
#665000
1$
#667000
1"
#672000
0$
#679000
1$
#686000
0$
#690000
1#
#693000
1$
#700000
0$
#713000
0"
#736000
0#
#759000
1"
#782000
1#
#805000
0"
#828000
0#
#851000
1"
#874000
1#
#897000
0"
#920000
0#
#943000
1"
#966000
1#
#989000
0"
#1012000
0#
#1035000
1"
#1058000
1#
#1081000
0"
#1104000
0#
#1127000
1"
#1150000
1#
#1173000
0"
#1196000
0#
#1219000
1"
#1242000
1#
#1265000
0"
#1288000
0#
#1311000
1"
#1334000
1#
#1357000
0"
#1380000
0#
#1403000
1"
#1426000
1#
#1449000
0"
#1472000
0#
#1495000
1"
#1518000
1#
#1541000
0"
#1564000
0#
