DigitalCircuit/FIFO/fifo.v
`timescale 1ns/1ps

module fifo(
    input clk,
    input rst,
    input [3:0] Data_In,
    output [7:0] Data_Out,
    output input_valid,  output_valid,
    input input_enable, output_enable);
// input clk;
// input [3:0] Data_In;
// input input_valid, input_enable, output_valid, output_enable;
// input rst;
// output [7:0] Data_Out;
reg [7:0] Data_Out;
reg [7:0] ram [7:0];
reg writelow;//写入低高位控制
reg [2:0]pos_write,pos_read;
reg input_valid,  output_valid;


always@(posedge clk)begin
  if(rst)begin
    // for(int i=0;i<7;i++)begin
    //     ram[i]=0;
    pos_read<=0;
    pos_write<=0;
    writelow<=1;
    Data_Out<=0;
    input_valid=1;
    output_valid=0;
    end
    else
    case({input_enable,input_valid,output_enable,output_valid})
        4'b1100://input
        begin 
            if(writelow)begin
            ram[pos_write][3:0]<=Data_In;
            writelow<=~writelow;
            // pos_write=pos_write+1;
            end
            else begin
            ram[pos_write][7:4]<=Data_In;
            writelow<=~writelow;
            pos_write<=pos_write+1;
            end

        if(!(pos_read==(pos_write+1)||(pos_write-7)==pos_read))
        begin
        input_valid<=1;
        output_valid<=0;
        end
        else
        begin
        input_valid<=0;
        output_valid<=1;
        end

        end


        4'b0011:
        begin
            Data_Out<=ram[pos_read];
            pos_read<=pos_read+1;
            input_valid<=1;
            output_valid<=0;
        end

        default:
        ;
    endcase
    end
endmodule

DigitalCircuit/FIFO/testfifo.v
`timescale 1ns/1ps
module test();

reg clk;
reg [3:0] Data_In;
reg input_enable,output_enable;
reg rst;
wire [7:0] Data_Out;
wire input_valid,output_valid;
// reg [7:0] Data_Out;
// reg [7:0] ram [7:0];
// reg writelow;//写入低高位控制
// reg [2:0]pos_write,pos_read;


fifo insfifo(clk,rst,Data_In,Data_Out,input_valid, output_valid, input_enable, output_enable);

initial
begin
  clk=0;
  rst=1;
  // input_valid=0;
  input_enable=0;
  // output_valid=0;
  output_enable=0;
  Data_In=0;
//   Data_Out=0;
$dumpfile("out.vcd");
$dumpvars(0,test);
$display("Start test.");
  #100
  $monitor(input_valid, input_enable, output_valid, output_enable,Data_In,Data_Out);
  setlong(30);
  set(1);
  set(0);
  set(2);
  set(0);
  set(0);
  set(1);
  set(3);
  set(3);
  set(3);
  set(3);
  set(3);
  set(3);
  set(3);
  set(3);
  set(3);
  set(3);
  get();
  set(0);
  set(2);
  get();
  set(0);
  set(0);
  get();
  set(0);
  set(0);
  get();
  setlong(1);
  get();
  setlong(1);
  get();
  setlong(1);
  get();
  setlong(1);
  get();
  setlong(1);
  get();
  setlong(1);
  get();
  repeat(1000)
  begin
  randomtest();
  end
  $finish;
  end

always #50 clk=~clk;

// always@(posedge clk)begin
task set(toset);
integer toset;
begin
Data_In=toset;
input_enable=1;
// input_valid=1;
output_enable=0;
// output_valid=0;
rst=0;
#100;
end
endtask

task get();
begin
rst=0;
input_enable=0;
// input_valid=0;
output_enable=1;
// output_valid=1;
#100;
$display("%d",Data_Out);
end
endtask

task setlong(integer a);
begin
set(a%'b10000);
set(a>>4);
end
endtask

task randomtest();
begin

input_enable=$random % 2;
output_enable=$random % 2;
Data_In=$random % 16;
#100;

end
endtask

endmodule

DigitalCircuit/FIFO/out.vcd
$date
	Wed Nov 22 22:52:34 2017
$end
$version
	Icarus Verilog
$end
$timescale
	1ps
$end
$scope module test $end
$var wire 1 ! output_valid $end
$var wire 1 " input_valid $end
$var wire 8 # Data_Out [7:0] $end
$var reg 4 $ Data_In [3:0] $end
$var reg 1 % clk $end
$var reg 1 & input_enable $end
$var reg 1 ' output_enable $end
$var reg 1 ( rst $end
$scope module insfifo $end
$var wire 4 ) Data_In [3:0] $end
$var wire 1 % clk $end
$var wire 1 & input_enable $end
$var wire 1 ' output_enable $end
$var wire 1 ( rst $end
$var reg 8 * Data_Out [7:0] $end
$var reg 1 " input_valid $end
$var reg 1 ! output_valid $end
$var reg 3 + pos_read [2:0] $end
$var reg 3 , pos_write [2:0] $end
$var reg 1 - writelow $end
$upscope $end
$scope task get $end
$upscope $end
$scope task randomtest $end
$upscope $end
$scope task set $end
$var integer 32 . toset [31:0] $end
$upscope $end
$scope task setlong $end
$var integer 32 / a [31:0] $end
$upscope $end
$upscope $end
$enddefinitions $end
#0
$dumpvars
bx /
bx .
x-
bx ,
bx +
bx *
b0 )
1(
0'
0&
0%
b0 $
bx #
x"
x!
$end
#50000
b0 #
b0 *
1-
b0 ,
b0 +
0!
1"
1%
#100000
0%
0(
1&
b1110 $
b1110 )
b1110 .
b11110 /
#150000
0-
1%
#200000
0%
b1 $
b1 )
b1 .
#250000
b1 ,
1-
1%
#300000
0%
#350000
0-
1%
#400000
0%
b0 $
b0 )
b0 .
#450000
b10 ,
1-
1%
#500000
0%
b10 $
b10 )
b10 .
#550000
0-
1%
#600000
0%
b0 $
b0 )
b0 .
#650000
b11 ,
1-
1%
#700000
0%
#750000
0-
1%
#800000
0%
b1 $
b1 )
b1 .
#850000
b100 ,
1-
1%
#900000
0%
b11 $
b11 )
b11 .
#950000
0-
1%
#1000000
0%
#1050000
b101 ,
1-
1%
#1100000
0%
#1150000
0-
1%
#1200000
0%
#1250000
b110 ,
1-
1%
#1300000
0%
#1350000
0-
1%
#1400000
0%
#1450000
b111 ,
1-
1%
#1500000
0%
#1550000
1!
0"
0-
1%
#1600000
0%
#1650000
1%
#1700000
0%
#1750000
1%
#1800000
0%
#1850000
1%
#1900000
0%
1'
0&
#1950000
0!
1"
b1 +
b11110 #
b11110 *
1%
#2000000
0%
0'
1&
b0 $
b0 )
b0 .
#2050000
b0 ,
1-
1%
#2100000
0%
b10 $
b10 )
b10 .
#2150000
1!
0"
0-
1%
#2200000
0%
1'
0&
#2250000
0!
1"
b10 +
b1 #
b1 *
1%
#2300000
0%
0'
1&
b0 $
b0 )
b0 .
#2350000
b1 ,
1-
1%
#2400000
0%
#2450000
1!
0"
0-
1%
#2500000
0%
1'
0&
#2550000
0!
1"
b11 +
b10 #
b10 *
1%
#2600000
0%
0'
1&
#2650000
b10 ,
1-
1%
#2700000
0%
#2750000
1!
0"
0-
1%
#2800000
0%
1'
0&
#2850000
0!
1"
b100 +
b10000 #
b10000 *
1%
#2900000
0%
0'
1&
b1 $
b1 )
b1 .
b1 /
#2950000
b11 ,
1-
1%
#3000000
0%
b0 $
b0 )
b0 .
#3050000
1!
0"
0-
1%
#3100000
0%
1'
0&
#3150000
0!
1"
b101 +
b110011 #
b110011 *
1%
#3200000
0%
0'
1&
b1 $
b1 )
b1 .
#3250000
b100 ,
1-
1%
#3300000
0%
b0 $
b0 )
b0 .
#3350000
1!
0"
0-
1%
#3400000
0%
1'
0&
#3450000
0!
1"
b110 +
1%
#3500000
0%
0'
1&
b1 $
b1 )
b1 .
#3550000
b101 ,
1-
1%
#3600000
0%
b0 $
b0 )
b0 .
#3650000
1!
0"
0-
1%
#3700000
0%
1'
0&
#3750000
0!
1"
b111 +
1%
#3800000
0%
0'
1&
b1 $
b1 )
b1 .
#3850000
b110 ,
1-
1%
#3900000
0%
b0 $
b0 )
b0 .
#3950000
1!
0"
0-
1%
#4000000
0%
1'
0&
#4050000
0!
1"
b0 +
b11 #
b11 *
1%
#4100000
0%
0'
1&
b1 $
b1 )
b1 .
#4150000
b111 ,
1-
1%
#4200000
0%
b0 $
b0 )
b0 .
#4250000
1!
0"
0-
1%
#4300000
0%
1'
0&
#4350000
0!
1"
b1 +
b10 #
b10 *
1%
#4400000
0%
0'
1&
b1 $
b1 )
b1 .
#4450000
b0 ,
1-
1%
#4500000
0%
b0 $
b0 )
b0 .
#4550000
1!
0"
0-
1%
#4600000
0%
1'
0&
#4650000
0!
1"
b10 +
b0 #
b0 *
1%
#4700000
0%
b1001 $
b1001 )
#4750000
1%
#4800000
0%
b1101 $
b1101 )
1&
#4850000
1%
#4900000
0%
b1 $
b1 )
0'
#4950000
b1 ,
1-
1%
#5000000
0%
b1101 $
b1101 )
#5050000
1!
0"
0-
1%
#5100000
0%
b1001 $
b1001 )
#5150000
1%
#5200000
0%
b1010 $
b1010 )
1'
0&
#5250000
0!
1"
b11 +
b10000 #
b10000 *
1%
#5300000
0%
b10 $
b10 )
1&
#5350000
1%
#5400000
0%
b1110 $
b1110 )
0'
#5450000
b10 ,
1-
1%
#5500000
0%
b1100 $
b1100 )
1'
0&
#5550000
1%
#5600000
0%
b101 $
b101 )
1&
#5650000
1%
#5700000
0%
b0 $
b0 )
0'
#5750000
1!
0"
0-
1%
#5800000
0%
b1101 $
b1101 )
0&
#5850000
1%
#5900000
0%
1'
#5950000
0!
1"
b100 +
1%
#6000000
0%
b101 $
b101 )
1&
#6050000
1%
#6100000
0%
b1101 $
b1101 )
0'
0&
#6150000
1%
#6200000
0%
b1010 $
b1010 )
1'
1&
#6250000
1%
#6300000
0%
b10 $
b10 )
0'
0&
#6350000
1%
#6400000
0%
b1000 $
b1000 )
1'
#6450000
1%
#6500000
0%
b1011 $
b1011 )
#6550000
1%
#6600000
0%
b1110 $
b1110 )
0'
#6650000
1%
#6700000
0%
b1011 $
b1011 )
#6750000
1%
#6800000
0%
b1111 $
b1111 )
1'
1&
#6850000
1%
#6900000
0%
b1110 $
b1110 )
0'
#6950000
b11 ,
1-
1%
#7000000
0%
b1001 $
b1001 )
1'
#7050000
1%
#7100000
0%
b1111 $
b1111 )
0'
0&
#7150000
1%
#7200000
0%
b111 $
b111 )
1&
#7250000
1!
0"
0-
1%
#7300000
0%
b1011 $
b1011 )
#7350000
1%
#7400000
0%
b0 $
b0 )
1'
#7450000
1%
#7500000
0%
b110 $
b110 )
#7550000
1%
#7600000
0%
b1000 $
b1000 )
0'
0&
#7650000
1%
#7700000
0%
b10 $
b10 )
1'
1&
#7750000
1%
#7800000
0%
b1001 $
b1001 )
0&
#7850000
0!
1"
b101 +
1%
#7900000
0%
b101 $
b101 )
1&
#7950000
1%
#8000000
0%
b1001 $
b1001 )
0&
#8050000
1%
#8100000
0%
b1000 $
b1000 )
0'
1&
#8150000
b100 ,
1-
1%
#8200000
0%
b1100 $
b1100 )
0&
#8250000
1%
#8300000
0%
b11 $
b11 )
#8350000
1%
#8400000
0%
1'
1&
#8450000
1%
#8500000
0%
b111 $
b111 )
0'
#8550000
1!
0"
0-
1%
#8600000
0%
b1010 $
b1010 )
#8650000
1%
#8700000
0%
1'
#8750000
1%
#8800000
0%
b1111 $
b1111 )
#8850000
1%
#8900000
0%
b0 $
b0 )
0'
#8950000
1%
#9000000
0%
b1110 $
b1110 )
1'
0&
#9050000
0!
1"
b110 +
1%
#9100000
0%
b1101 $
b1101 )
0'
#9150000
1%
#9200000
0%
b1110 $
b1110 )
1&
#9250000
b101 ,
1-
1%
#9300000
0%
b110 $
b110 )
#9350000
1!
0"
0-
1%
#9400000
0%
b1000 $
b1000 )
1'
0&
#9450000
0!
1"
b111 +
1%
#9500000
0%
b100 $
b100 )
#9550000
1%
#9600000
0%
b1101 $
b1101 )
1&
#9650000
1%
#9700000
0%
b110 $
b110 )
#9750000
1%
#9800000
0%
b101 $
b101 )
0'
0&
#9850000
1%
#9900000
0%
b111 $
b111 )
#9950000
1%
#10000000
0%
b1000 $
b1000 )
1&
#10050000
b110 ,
1-
1%
#10100000
0%
b111 $
b111 )
1'
0&
#10150000
1%
#10200000
0%
b1100 $
b1100 )
0'
#10250000
1%
#10300000
0%
1'
1&
#10350000
1%
#10400000
0%
b1101 $
b1101 )
0'
0&
#10450000
1%
#10500000
0%
b11 $
b11 )
#10550000
1%
#10600000
0%
b1010 $
b1010 )
#10650000
1%
#10700000
0%
b1001 $
b1001 )
1&
#10750000
1!
0"
0-
1%
#10800000
0%
b0 $
b0 )
#10850000
1%
#10900000
0%
b1101 $
b1101 )
0&
#10950000
1%
#11000000
0%
b1000 $
b1000 )
#11050000
1%
#11100000
0%
b1111 $
b1111 )
1'
#11150000
0!
1"
b0 +
1%
#11200000
0%
b1 $
b1 )
0'
1&
#11250000
b111 ,
1-
1%
#11300000
0%
b110 $
b110 )
1'
#11350000
1%
#11400000
0%
b101 $
b101 )
0&
#11450000
1%
#11500000
0%
1&
#11550000
1%
#11600000
0%
b11 $
b11 )
0&
#11650000
1%
#11700000
0%
b1110 $
b1110 )
0'
#11750000
1%
#11800000
0%
b1 $
b1 )
1'
#11850000
1%
#11900000
0%
b1111 $
b1111 )
0'
#11950000
1%
#12000000
0%
b1101 $
b1101 )
#12050000
1%
#12100000
0%
b1001 $
b1001 )
#12150000
1%
#12200000
0%
b11 $
b11 )
#12250000
1%
#12300000
0%
b110 $
b110 )
1'
1&
#12350000
1%
#12400000
0%
b1001 $
b1001 )
0'
0&
#12450000
1%
#12500000
0%
b1111 $
b1111 )
#12550000
1%
#12600000
0%
b10 $
b10 )
#12650000
1%
#12700000
0%
b100 $
b100 )
1'
#12750000
1%
#12800000
0%
b1001 $
b1001 )
0'
#12850000
1%
#12900000
0%
b1011 $
b1011 )
1&
#12950000
1!
0"
0-
1%
#13000000
0%
b1001 $
b1001 )
1'
#13050000
1%
#13100000
0%
b1111 $
b1111 )
0&
#13150000
0!
1"
b1 +
1%
#13200000
0%
b1110 $
b1110 )
0'
1&
#13250000
b0 ,
1-
1%
#13300000
0%
b1000 $
b1000 )
#13350000
1!
0"
0-
1%
#13400000
0%
b10 $
b10 )
1'
#13450000
1%
#13500000
0%
b1100 $
b1100 )
0&
#13550000
0!
1"
b10 +
b11101101 #
b11101101 *
1%
#13600000
0%
b110 $
b110 )
#13650000
1%
#13700000
0%
b1000 $
b1000 )
1&
#13750000
1%
#13800000
0%
b1011 $
b1011 )
0'
#13850000
b1 ,
1-
1%
#13900000
0%
b11 $
b11 )
0&
#13950000
1%
#14000000
0%
b1000 $
b1000 )
#14050000
1%
#14100000
0%
b1 $
b1 )
1'
1&
#14150000
1%
#14200000
0%
b1000 $
b1000 )
#14250000
1%
#14300000
0%
b1111 $
b1111 )
#14350000
1%
#14400000
0%
b110 $
b110 )
0'
0&
#14450000
1%
#14500000
0%
#14550000
1%
#14600000
0%
b1101 $
b1101 )
1'
1&
#14650000
1%
#14700000
0%
#14750000
1%
#14800000
0%
b111 $
b111 )
0'
#14850000
1!
0"
0-
1%
#14900000
0%
b1001 $
b1001 )
1'
#14950000
1%
#15000000
0%
b1 $
b1 )
#15050000
1%
#15100000
0%
b1010 $
b1010 )
0'
#15150000
1%
#15200000
0%
b1100 $
b1100 )
1'
#15250000
1%
#15300000
0%
b1000 $
b1000 )
0'
0&
#15350000
1%
#15400000
0%
b0 $
b0 )
1&
#15450000
1%
#15500000
0%
b1000 $
b1000 )
0&
#15550000
1%
#15600000
0%
b0 $
b0 )
1'
#15650000
0!
1"
b11 +
b11100000 #
b11100000 *
1%
#15700000
0%
#15750000
1%
#15800000
0%
b10 $
b10 )
0'
#15850000
1%
#15900000
0%
b111 $
b111 )
1'
1&
#15950000
1%
#16000000
0%
b110 $
b110 )
#16050000
1%
#16100000
0%
b1101 $
b1101 )
#16150000
1%
#16200000
0%
b1100 $
b1100 )
0&
#16250000
1%
#16300000
0%
b1011 $
b1011 )
#16350000
1%
#16400000
0%
b1110 $
b1110 )
#16450000
1%
#16500000
0%
b0 $
b0 )
#16550000
1%
#16600000
0%
b100 $
b100 )
0'
#16650000
1%
#16700000
0%
b1011 $
b1011 )
1'
1&
#16750000
1%
#16800000
0%
b1101 $
b1101 )
0'
#16850000
b10 ,
1-
1%
#16900000
0%
b11 $
b11 )
1'
#16950000
1%
#17000000
0%
b1 $
b1 )
#17050000
1%
#17100000
0%
b0 $
b0 )
0&
#17150000
1%
#17200000
0%
b1000 $
b1000 )
0'
1&
#17250000
1!
0"
0-
1%
#17300000
0%
b100 $
b100 )
#17350000
1%
#17400000
0%
b0 $
b0 )
0&
#17450000
1%
#17500000
0%
b100 $
b100 )
1&
#17550000
1%
#17600000
0%
b0 $
b0 )
0&
#17650000
1%
#17700000
0%
b110 $
b110 )
1'
#17750000
0!
1"
b100 +
b10000111 #
b10000111 *
1%
#17800000
0%
b10 $
b10 )
0'
1&
#17850000
b11 ,
1-
1%
#17900000
0%
b1101 $
b1101 )
#17950000
1!
0"
0-
1%
#18000000
0%
b111 $
b111 )
#18050000
1%
#18100000
0%
b100 $
b100 )
1'
0&
#18150000
0!
1"
b101 +
b11100111 #
b11100111 *
1%
#18200000
0%
b1100 $
b1100 )
0'
#18250000
1%
#18300000
0%
b1 $
b1 )
1&
#18350000
b100 ,
1-
1%
#18400000
0%
b11 $
b11 )
1'
0&
#18450000
1%
#18500000
0%
b100 $
b100 )
#18550000
1%
#18600000
0%
b1111 $
b1111 )
1&
#18650000
1%
#18700000
0%
b1101 $
b1101 )
0&
#18750000
1%
#18800000
0%
b1001 $
b1001 )
0'
#18850000
1%
#18900000
0%
b1100 $
b1100 )
1&
#18950000
1!
0"
0-
1%
#19000000
0%
b1010 $
b1010 )
1'
#19050000
1%
#19100000
0%
0&
#19150000
0!
1"
b110 +
b10000110 #
b10000110 *
1%
#19200000
0%
b1001 $
b1001 )
#19250000
1%
#19300000
0%
0'
#19350000
1%
#19400000
0%
b111 $
b111 )
#19450000
1%
#19500000
0%
b1011 $
b1011 )
1&
#19550000
b101 ,
1-
1%
#19600000
0%
b1001 $
b1001 )
1'
0&
#19650000
1%
#19700000
0%
b101 $
b101 )
#19750000
1%
#19800000
0%
b1 $
b1 )
0'
1&
#19850000
1!
0"
0-
1%
#19900000
0%
b1010 $
b1010 )
1'
#19950000
1%
#20000000
0%
b100 $
b100 )
0&
#20050000
0!
1"
b111 +
b11001 #
b11001 *
1%
#20100000
0%
b110 $
b110 )
#20150000
1%
#20200000
0%
b101 $
b101 )
#20250000
1%
#20300000
0%
b110 $
b110 )
#20350000
1%
#20400000
0%
b1 $
b1 )
1&
#20450000
1%
#20500000
0%
b10 $
b10 )
0'
#20550000
b110 ,
1-
1%
#20600000
0%
b1111 $
b1111 )
#20650000
1!
0"
0-
1%
#20700000
0%
b1001 $
b1001 )
1'
0&
#20750000
0!
1"
b0 +
b11101011 #
b11101011 *
1%
#20800000
0%
b1111 $
b1111 )
0'
#20850000
1%
#20900000
0%
b1110 $
b1110 )
1'
1&
#20950000
1%
#21000000
0%
b1000 $
b1000 )
0&
#21050000
1%
#21100000
0%
b1 $
b1 )
#21150000
1%
#21200000
0%
0'
1&
#21250000
b111 ,
1-
1%
#21300000
0%
b0 $
b0 )
#21350000
1!
0"
0-
1%
#21400000
0%
b1 $
b1 )
1'
0&
#21450000
0!
1"
b1 +
b10111000 #
b10111000 *
1%
#21500000
0%
b10 $
b10 )
0'
1&
#21550000
b0 ,
1-
1%
#21600000
0%
b1111 $
b1111 )
1'
0&
#21650000
1%
#21700000
0%
b1010 $
b1010 )
1&
#21750000
1%
#21800000
0%
b11 $
b11 )
#21850000
1%
#21900000
0%
b111 $
b111 )
#21950000
1%
#22000000
0%
b1 $
b1 )
0'
#22050000
1!
0"
0-
1%
#22100000
0%
b1010 $
b1010 )
0&
#22150000
1%
#22200000
0%
b101 $
b101 )
1'
1&
#22250000
1%
#22300000
0%
b1 $
b1 )
#22350000
1%
#22400000
0%
b1101 $
b1101 )
#22450000
1%
#22500000
0%
b10 $
b10 )
0'
0&
#22550000
1%
#22600000
0%
b1100 $
b1100 )
1&
#22650000
1%
#22700000
0%
b101 $
b101 )
1'
0&
#22750000
0!
1"
b10 +
b11010111 #
b11010111 *
1%
#22800000
0%
b1100 $
b1100 )
0'
#22850000
1%
#22900000
0%
b1000 $
b1000 )
1'
1&
#22950000
1%
#23000000
0%
b11 $
b11 )
0'
#23050000
b1 ,
1-
1%
#23100000
0%
b100 $
b100 )
0&
#23150000
1%
#23200000
0%
b11 $
b11 )
1'
1&
#23250000
1%
#23300000
0%
b1100 $
b1100 )
0&
#23350000
1%
#23400000
0%
b101 $
b101 )
0'
1&
#23450000
1!
0"
0-
1%
#23500000
0%
b10 $
b10 )
#23550000
1%
#23600000
0%
b1101 $
b1101 )
0&
#23650000
1%
#23700000
0%
b0 $
b0 )
1&
#23750000
1%
#23800000
0%
b1011 $
b1011 )
#23850000
1%
#23900000
0%
b1101 $
b1101 )
1'
0&
#23950000
0!
1"
b11 +
b101000 #
b101000 *
1%
#24000000
0%
b1001 $
b1001 )
#24050000
1%
#24100000
0%
b0 $
b0 )
0'
#24150000
1%
#24200000
0%
b1101 $
b1101 )
1'
#24250000
1%
#24300000
0%
1&
#24350000
1%
#24400000
0%
b1100 $
b1100 )
0'
0&
#24450000
1%
#24500000
0%
b1010 $
b1010 )
#24550000
1%
#24600000
0%
b11 $
b11 )
1'
#24650000
1%
#24700000
0%
b101 $
b101 )
1&
#24750000
1%
#24800000
0%
b110 $
b110 )
#24850000
1%
#24900000
0%
b0 $
b0 )
0'
0&
#24950000
1%
#25000000
0%
b1001 $
b1001 )
#25050000
1%
#25100000
0%
b1111 $
b1111 )
1&
#25150000
b10 ,
1-
1%
#25200000
0%
b1101 $
b1101 )
1'
0&
#25250000
1%
#25300000
0%
b1100 $
b1100 )
0'
1&
#25350000
1!
0"
0-
1%
#25400000
0%
b101 $
b101 )
1'
0&
#25450000
0!
1"
b100 +
b11101 #
b11101 *
1%
#25500000
0%
b1000 $
b1000 )
#25550000
1%
#25600000
0%
b110 $
b110 )
0'
#25650000
1%
#25700000
0%
b101 $
b101 )
#25750000
1%
#25800000
0%
b11 $
b11 )
#25850000
1%
#25900000
0%
b1001 $
b1001 )
#25950000
1%
#26000000
0%
b1000 $
b1000 )
1'
1&
#26050000
1%
#26100000
0%
b1111 $
b1111 )
0&
#26150000
1%
#26200000
0%
b1000 $
b1000 )
1&
#26250000
1%
#26300000
0%
b1011 $
b1011 )
#26350000
1%
#26400000
0%
b1101 $
b1101 )
0'
#26450000
b11 ,
1-
1%
#26500000
0%
b111 $
b111 )
0&
#26550000
1%
#26600000
0%
b1001 $
b1001 )
#26650000
1%
#26700000
0%
b1010 $
b1010 )
#26750000
1%
#26800000
0%
b1100 $
b1100 )
#26850000
1%
#26900000
0%
1'
1&
#26950000
1%
#27000000
0%
b1 $
b1 )
0&
#27050000
1%
#27100000
0%
b1001 $
b1001 )
1&
#27150000
1%
#27200000
0%
b0 $
b0 )
#27250000
1%
#27300000
0%
b10 $
b10 )
0'
#27350000
1!
0"
0-
1%
#27400000
0%
b111 $
b111 )
1'
0&
#27450000
0!
1"
b101 +
b10111100 #
b10111100 *
1%
#27500000
0%
b1101 $
b1101 )
#27550000
1%
#27600000
0%
b1000 $
b1000 )
0'
1&
#27650000
b100 ,
1-
1%
#27700000
0%
b101 $
b101 )
0&
#27750000
1%
#27800000
0%
b1110 $
b1110 )
1'
1&
#27850000
1%
#27900000
0%
b1000 $
b1000 )
0'
#27950000
1!
0"
0-
1%
#28000000
0%
b110 $
b110 )
0&
#28050000
1%
#28100000
0%
b101 $
b101 )
#28150000
1%
#28200000
0%
b11 $
b11 )
#28250000
1%
#28300000
0%
b111 $
b111 )
1'
1&
#28350000
1%
#28400000
0%
b1010 $
b1010 )
0'
#28450000
1%
#28500000
0%
b1011 $
b1011 )
0&
#28550000
1%
#28600000
0%
b100 $
b100 )
1&
#28650000
1%
#28700000
0%
b101 $
b101 )
1'
#28750000
1%
#28800000
0%
b0 $
b0 )
#28850000
1%
#28900000
0%
b111 $
b111 )
0'
0&
#28950000
1%
#29000000
0%
b1110 $
b1110 )
1'
#29050000
0!
1"
b110 +
b100001 #
b100001 *
1%
#29100000
0%
b0 $
b0 )
0'
#29150000
1%
#29200000
0%
b1000 $
b1000 )
1'
#29250000
1%
#29300000
0%
1&
#29350000
1%
#29400000
0%
b1010 $
b1010 )
#29450000
1%
#29500000
0%
b1011 $
b1011 )
0'
#29550000
b101 ,
1-
1%
#29600000
0%
b1100 $
b1100 )
#29650000
1!
0"
0-
1%
#29700000
0%
b0 $
b0 )
1'
#29750000
1%
#29800000
0%
0'
0&
#29850000
1%
#29900000
0%
b1101 $
b1101 )
1'
1&
#29950000
1%
#30000000
0%
b111 $
b111 )
0'
0&
#30050000
1%
#30100000
0%
b1011 $
b1011 )
1'
1&
#30150000
1%
#30200000
0%
b1001 $
b1001 )
0'
0&
#30250000
1%
#30300000
0%
b1110 $
b1110 )
1&
#30350000
1%
#30400000
0%
b1011 $
b1011 )
#30450000
1%
#30500000
0%
b101 $
b101 )
1'
0&
#30550000
0!
1"
b111 +
b11111 #
b11111 *
1%
#30600000
0%
b10 $
b10 )
0'
#30650000
1%
#30700000
0%
b11 $
b11 )
#30750000
1%
#30800000
0%
b1010 $
b1010 )
1'
#30850000
1%
#30900000
0%
b1011 $
b1011 )
0'
#30950000
1%
#31000000
0%
b111 $
b111 )
#31050000
1%
#31100000
0%
b1 $
b1 )
1'
#31150000
1%
#31200000
0%
b101 $
b101 )
1&
#31250000
1%
#31300000
0%
b1111 $
b1111 )
0&
#31350000
1%
#31400000
0%
b1101 $
b1101 )
0'
#31450000
1%
#31500000
0%
b1001 $
b1001 )
1'
#31550000
1%
#31600000
0%
b1011 $
b1011 )
1&
#31650000
1%
#31700000
0%
b1000 $
b1000 )
0&
#31750000
1%
#31800000
0%
b101 $
b101 )
0'
1&
#31850000
b110 ,
1-
1%
#31900000
0%
b100 $
b100 )
#31950000
1!
0"
0-
1%
#32000000
0%
b1111 $
b1111 )
0&
#32050000
1%
#32100000
0%
b10 $
b10 )
1&
#32150000
1%
#32200000
0%
b111 $
b111 )
1'
#32250000
1%
#32300000
0%
b1000 $
b1000 )
#32350000
1%
#32400000
0%
b0 $
b0 )
0'
0&
#32450000
1%
#32500000
0%
b1100 $
b1100 )
1&
#32550000
1%
#32600000
0%
b1001 $
b1001 )
#32650000
1%
#32700000
0%
b101 $
b101 )
0&
#32750000
1%
#32800000
0%
b10 $
b10 )
#32850000
1%
#32900000
0%
b1010 $
b1010 )
1'
#32950000
0!
1"
b0 +
b100000 #
b100000 *
1%
#33000000
0%
b10 $
b10 )
1&
#33050000
1%
#33100000
0%
b1110 $
b1110 )
0&
#33150000
1%
#33200000
0%
b1111 $
b1111 )
1&
#33250000
1%
#33300000
0%
b1001 $
b1001 )
0'
#33350000
b111 ,
1-
1%
#33400000
0%
b1 $
b1 )
0&
#33450000
1%
#33500000
0%
b100 $
b100 )
1'
1&
#33550000
1%
#33600000
0%
b1001 $
b1001 )
#33650000
1%
#33700000
0%
b1 $
b1 )
#33750000
1%
#33800000
0%
b100 $
b100 )
0&
#33850000
1%
#33900000
0%
b1011 $
b1011 )
0'
#33950000
1%
#34000000
0%
b10 $
b10 )
1'
#34050000
1%
#34100000
0%
b0 $
b0 )
0'
1&
#34150000
1!
0"
0-
1%
#34200000
0%
b1011 $
b1011 )
0&
#34250000
1%
#34300000
0%
b1111 $
b1111 )
#34350000
1%
#34400000
0%
b0 $
b0 )
1'
#34450000
0!
1"
b1 +
b110001 #
b110001 *
1%
#34500000
0%
b1011 $
b1011 )
#34550000
1%
#34600000
0%
b1001 $
b1001 )
0'
#34650000
1%
#34700000
0%
b101 $
b101 )
1&
#34750000
b0 ,
1-
1%
#34800000
0%
b1111 $
b1111 )
1'
#34850000
1%
#34900000
0%
b1100 $
b1100 )
0&
#34950000
1%
#35000000
0%
b1 $
b1 )
#35050000
1%
#35100000
0%
b1001 $
b1001 )
#35150000
1%
#35200000
0%
b1111 $
b1111 )
#35250000
1%
#35300000
0%
b1011 $
b1011 )
0'
1&
#35350000
1!
0"
0-
1%
#35400000
0%
b1110 $
b1110 )
1'
0&
#35450000
0!
1"
b10 +
b11110101 #
b11110101 *
1%
#35500000
0%
b1010 $
b1010 )
0'
#35550000
1%
#35600000
0%
#35650000
1%
#35700000
0%
b1001 $
b1001 )
#35750000
1%
#35800000
0%
b1110 $
b1110 )
1'
1&
#35850000
1%
#35900000
0%
b101 $
b101 )
0'
0&
#35950000
1%
#36000000
0%
b111 $
b111 )
1&
#36050000
b1 ,
1-
1%
#36100000
0%
b1110 $
b1110 )
1'
#36150000
1%
#36200000
0%
b1101 $
b1101 )
0&
#36250000
1%
#36300000
0%
b1100 $
b1100 )
0'
#36350000
1%
#36400000
0%
1'
#36450000
1%
#36500000
0%
1&
#36550000
1%
#36600000
0%
b1111 $
b1111 )
0'
#36650000
1!
0"
0-
1%
#36700000
0%
b1011 $
b1011 )
#36750000
1%
#36800000
0%
b11 $
b11 )
1'
#36850000
1%
#36900000
0%
b110 $
b110 )
0&
#36950000
0!
1"
b11 +
b11011100 #
b11011100 *
1%
#37000000
0%
b1010 $
b1010 )
0'
1&
#37050000
b10 ,
1-
1%
#37100000
0%
b1001 $
b1001 )
0&
#37150000
1%
#37200000
0%
b110 $
b110 )
1'
#37250000
1%
#37300000
0%
b1111 $
b1111 )
#37350000
1%
#37400000
0%
b1100 $
b1100 )
1&
#37450000
1%
#37500000
0%
b1001 $
b1001 )
#37550000
1%
#37600000
0%
b1101 $
b1101 )
0'
0&
#37650000
1%
#37700000
0%
b0 $
b0 )
1'
1&
#37750000
1%
#37800000
0%
b100 $
b100 )
#37850000
1%
#37900000
0%
b110 $
b110 )
0&
#37950000
1%
#38000000
0%
b1001 $
b1001 )
#38050000
1%
#38100000
0%
0'
#38150000
1%
#38200000
0%
b1100 $
b1100 )
#38250000
1%
#38300000
0%
b1 $
b1 )
1'
1&
#38350000
1%
#38400000
0%
b11 $
b11 )
#38450000
1%
#38500000
0%
b1110 $
b1110 )
0&
#38550000
1%
#38600000
0%
b1101 $
b1101 )
0'
1&
#38650000
1!
0"
0-
1%
#38700000
0%
b100 $
b100 )
1'
0&
#38750000
0!
1"
b100 +
b10000010 #
b10000010 *
1%
#38800000
0%
b1001 $
b1001 )
0'
1&
#38850000
b11 ,
1-
1%
#38900000
0%
b110 $
b110 )
1'
0&
#38950000
1%
#39000000
0%
b111 $
b111 )
0'
#39050000
1%
#39100000
0%
b1101 $
b1101 )
