DigitalCircuit/FIFO/fifo.v
`timescale 1ns/1ps

module fifo(
    input clk,
    input rst,
    input [3:0] Data_In,
    output [7:0] Data_Out,
    output input_valid,  output_valid,
    input input_enable, output_enable);
// input clk;
// input [3:0] Data_In;
// input input_valid, input_enable, output_valid, output_enable;
// input rst;
// output [7:0] Data_Out;
reg [7:0] Data_Out;
reg [7:0] ram [7:0];
reg writelow;//写入低高位控制
reg [2:0]pos_write,pos_read;
reg input_valid,  output_valid;


always@(posedge clk)begin
  if(rst)begin
    // for(int i=0;i<7;i++)begin
    //     ram[i]=0;
    pos_read<=0;
    pos_write<=0;
    writelow<=1;
    Data_Out<=0;
    input_valid=1;
    output_valid=0;
    end
    else
    case({input_enable,input_valid,output_enable,output_valid})
        4'b1100://input
        begin
            if(!(pos_read==(pos_write+1)||(pos_write-7)==pos_read))
            begin     
            if(writelow)begin
            ram[pos_write][3:0]<=Data_In;
            writelow<=~writelow;
            // pos_write=pos_write+1;
            end
            else begin
            ram[pos_write][7:4]<=Data_In;
            writelow<=~writelow;
            pos_write<=pos_write+1;
            end
            end

        if(!(pos_read==(pos_write+1)||(pos_write-7)==pos_read))
        begin
        input_valid<=1;
        output_valid<=0;
        end
        else
        begin
        input_valid<=0;
        output_valid<=1;
        end

        end


        4'b0011:
        begin
            if(pos_read===(pos_write+1)||pos_read===(pos_write-7))begin
            Data_Out<=ram[pos_read];
            pos_read<=pos_read+1;
            input_valid<=1;
            output_valid<=0;
            end
        
        end

        default:
        ;
    endcase
    end
endmodule

DigitalCircuit/FIFO/testfifo.v
`timescale 1ns/1ps
module test();

reg clk;
reg [3:0] Data_In;
reg input_enable,output_enable;
reg rst;
wire [7:0] Data_Out;
wire input_valid,output_valid;
// reg [7:0] Data_Out;
// reg [7:0] ram [7:0];
// reg writelow;//写入低高位控制
// reg [2:0]pos_write,pos_read;


fifo insfifo(clk,rst,Data_In,Data_Out,input_valid, output_valid, input_enable, output_enable);

initial
begin
  clk=0;
  rst=1;
  // input_valid=0;
  input_enable=0;
  // output_valid=0;
  output_enable=0;
  Data_In=0;
//   Data_Out=0;
$dumpfile("out.vcd");
$dumpvars(0,test);
$display("Start test.");
  #100
  $monitor(input_valid, input_enable, output_valid, output_enable,Data_In,Data_Out);
  setlong(30);
  set(1);
  set(0);
  set(2);
  set(0);
  set(0);
  set(1);
  set(3);
  set(3);
  set(3);
  set(3);
  set(3);
  set(3);
  set(3);
  set(3);
  set(3);
  set(3);
  get();
  set(0);
  set(2);
  get();
  set(0);
  set(0);
  get();
  set(0);
  set(0);
  get();
  setlong(1);
  get();
  setlong(1);
  get();
  setlong(1);
  get();
  setlong(1);
  get();
  setlong(1);
  get();
  setlong(1);
  get();
  repeat(100)
  begin
  randomtest();
  end
  $finish;
  end

always #50 clk=~clk;

// always@(posedge clk)begin
task set(toset);
integer toset;
begin
Data_In=toset;
input_enable=1;
// input_valid=1;
output_enable=0;
// output_valid=0;
rst=0;
#100;
end
endtask

task get();
begin
rst=0;
input_enable=0;
// input_valid=0;
output_enable=1;
// output_valid=1;
#100;
$display("%d",Data_Out);
end
endtask

task setlong(integer a);
begin
set(a%'b10000);
set(a>>4);
end
endtask

task randomtest();
begin

input_enable=$random % 2;
output_enable=$random % 2;
Data_In=$random % 16;
#100;

end
endtask

endmodule

DigitalCircuit/FIFO/out.vcd
$date
	Wed Nov 22 22:45:15 2017
$end
$version
	Icarus Verilog
$end
$timescale
	1ps
$end
$scope module test $end
$var wire 1 ! output_valid $end
$var wire 1 " input_valid $end
$var wire 8 # Data_Out [7:0] $end
$var reg 4 $ Data_In [3:0] $end
$var reg 1 % clk $end
$var reg 1 & input_enable $end
$var reg 1 ' output_enable $end
$var reg 1 ( rst $end
$scope module insfifo $end
$var wire 4 ) Data_In [3:0] $end
$var wire 1 % clk $end
$var wire 1 & input_enable $end
$var wire 1 ' output_enable $end
$var wire 1 ( rst $end
$var reg 8 * Data_Out [7:0] $end
$var reg 1 " input_valid $end
$var reg 1 ! output_valid $end
$var reg 3 + pos_read [2:0] $end
$var reg 3 , pos_write [2:0] $end
$var reg 1 - writelow $end
$upscope $end
$scope task get $end
$upscope $end
$scope task randomtest $end
$upscope $end
$scope task set $end
$var integer 32 . toset [31:0] $end
$upscope $end
$scope task setlong $end
$var integer 32 / a [31:0] $end
$upscope $end
$upscope $end
$enddefinitions $end
#0
$dumpvars
bx /
bx .
x-
bx ,
bx +
bx *
b0 )
1(
0'
0&
0%
b0 $
bx #
x"
x!
$end
#50000
b0 #
b0 *
1-
b0 ,
b0 +
0!
1"
1%
#100000
0%
0(
1&
b1110 $
b1110 )
b1110 .
b11110 /
#150000
0-
1%
#200000
0%
b1 $
b1 )
b1 .
#250000
b1 ,
1-
1%
#300000
0%
#350000
0-
1%
#400000
0%
b0 $
b0 )
b0 .
#450000
b10 ,
1-
1%
#500000
0%
b10 $
b10 )
b10 .
#550000
0-
1%
#600000
0%
b0 $
b0 )
b0 .
#650000
b11 ,
1-
1%
#700000
0%
#750000
0-
1%
#800000
0%
b1 $
b1 )
b1 .
#850000
b100 ,
1-
1%
#900000
0%
b11 $
b11 )
b11 .
#950000
0-
1%
#1000000
0%
#1050000
b101 ,
1-
1%
#1100000
0%
#1150000
0-
1%
#1200000
0%
#1250000
b110 ,
1-
1%
#1300000
0%
#1350000
0-
1%
#1400000
0%
#1450000
b111 ,
1-
1%
#1500000
0%
#1550000
1!
0"
1%
#1600000
0%
#1650000
1%
#1700000
0%
#1750000
1%
#1800000
0%
#1850000
1%
#1900000
0%
1'
0&
#1950000
0!
1"
b1 +
b11110 #
b11110 *
1%
#2000000
0%
0'
1&
b0 $
b0 )
b0 .
#2050000
0-
1%
#2100000
0%
b10 $
b10 )
b10 .
#2150000
b0 ,
1-
1%
#2200000
0%
1'
0&
#2250000
1%
#2300000
0%
0'
1&
b0 $
b0 )
b0 .
#2350000
1!
0"
1%
#2400000
0%
#2450000
1%
#2500000
0%
1'
0&
#2550000
0!
1"
b10 +
b1 #
b1 *
1%
#2600000
0%
0'
1&
#2650000
0-
1%
#2700000
0%
#2750000
b1 ,
1-
1%
#2800000
0%
1'
0&
#2850000
1%
#2900000
0%
0'
1&
b1 $
b1 )
b1 .
b1 /
#2950000
1!
0"
1%
#3000000
0%
b0 $
b0 )
b0 .
#3050000
1%
#3100000
0%
1'
0&
#3150000
0!
1"
b11 +
b10 #
b10 *
1%
#3200000
0%
0'
1&
b1 $
b1 )
b1 .
#3250000
0-
1%
#3300000
0%
b0 $
b0 )
b0 .
#3350000
b10 ,
1-
1%
#3400000
0%
1'
0&
#3450000
1%
#3500000
0%
0'
1&
b1 $
b1 )
b1 .
#3550000
1!
0"
1%
#3600000
0%
b0 $
b0 )
b0 .
#3650000
1%
#3700000
0%
1'
0&
#3750000
0!
1"
b100 +
b10000 #
b10000 *
1%
#3800000
0%
0'
1&
b1 $
b1 )
b1 .
#3850000
0-
1%
#3900000
0%
b0 $
b0 )
b0 .
#3950000
b11 ,
1-
1%
#4000000
0%
1'
0&
#4050000
1%
#4100000
0%
0'
1&
b1 $
b1 )
b1 .
#4150000
1!
0"
1%
#4200000
0%
b0 $
b0 )
b0 .
#4250000
1%
#4300000
0%
1'
0&
#4350000
0!
1"
b101 +
b110011 #
b110011 *
1%
#4400000
0%
0'
1&
b1 $
b1 )
b1 .
#4450000
0-
1%
#4500000
0%
b0 $
b0 )
b0 .
#4550000
b100 ,
1-
1%
#4600000
0%
1'
0&
#4650000
1%
#4700000
0%
b1001 $
b1001 )
#4750000
1%
#4800000
0%
b1101 $
b1101 )
1&
#4850000
1%
#4900000
0%
b1 $
b1 )
0'
#4950000
1!
0"
1%
#5000000
0%
b1101 $
b1101 )
#5050000
1%
#5100000
0%
b1001 $
b1001 )
#5150000
1%
#5200000
0%
b1010 $
b1010 )
1'
0&
#5250000
0!
1"
b110 +
1%
#5300000
0%
b10 $
b10 )
1&
#5350000
1%
#5400000
0%
b1110 $
b1110 )
0'
#5450000
0-
1%
#5500000
0%
b1100 $
b1100 )
1'
0&
#5550000
1%
#5600000
0%
b101 $
b101 )
1&
#5650000
1%
#5700000
0%
b0 $
b0 )
0'
#5750000
b101 ,
1-
1%
#5800000
0%
b1101 $
b1101 )
0&
#5850000
1%
#5900000
0%
1'
#5950000
1%
#6000000
0%
b101 $
b101 )
1&
#6050000
1%
#6100000
0%
b1101 $
b1101 )
0'
0&
#6150000
1%
#6200000
0%
b1010 $
b1010 )
1'
1&
#6250000
1%
#6300000
0%
b10 $
b10 )
0'
0&
#6350000
1%
#6400000
0%
b1000 $
b1000 )
1'
#6450000
1%
#6500000
0%
b1011 $
b1011 )
#6550000
1%
#6600000
0%
b1110 $
b1110 )
0'
#6650000
1%
#6700000
0%
b1011 $
b1011 )
#6750000
1%
#6800000
0%
b1111 $
b1111 )
1'
1&
#6850000
1%
#6900000
0%
b1110 $
b1110 )
0'
#6950000
1!
0"
1%
#7000000
0%
b1001 $
b1001 )
1'
#7050000
1%
#7100000
0%
b1111 $
b1111 )
0'
0&
#7150000
1%
#7200000
0%
b111 $
b111 )
1&
#7250000
1%
#7300000
0%
b1011 $
b1011 )
#7350000
1%
#7400000
0%
b0 $
b0 )
1'
#7450000
1%
#7500000
0%
b110 $
b110 )
#7550000
1%
#7600000
0%
b1000 $
b1000 )
0'
0&
#7650000
1%
#7700000
0%
b10 $
b10 )
1'
1&
#7750000
1%
#7800000
0%
b1001 $
b1001 )
0&
#7850000
0!
1"
b111 +
1%
#7900000
0%
b101 $
b101 )
1&
#7950000
1%
#8000000
0%
b1001 $
b1001 )
0&
#8050000
1%
#8100000
0%
b1000 $
b1000 )
0'
1&
#8150000
0-
1%
#8200000
0%
b1100 $
b1100 )
0&
#8250000
1%
#8300000
0%
b11 $
b11 )
#8350000
1%
#8400000
0%
1'
1&
#8450000
1%
#8500000
0%
b111 $
b111 )
0'
#8550000
b110 ,
1-
1%
#8600000
0%
b1010 $
b1010 )
#8650000
1!
0"
1%
#8700000
0%
1'
#8750000
1%
#8800000
0%
b1111 $
b1111 )
#8850000
1%
#8900000
0%
b0 $
b0 )
0'
#8950000
1%
#9000000
0%
b1110 $
b1110 )
1'
0&
#9050000
0!
1"
b0 +
b100000 #
b100000 *
1%
#9100000
0%
b1101 $
b1101 )
0'
#9150000
1%
#9200000
0%
b1110 $
b1110 )
1&
#9250000
0-
1%
#9300000
0%
b110 $
b110 )
#9350000
b111 ,
1-
1%
#9400000
0%
b1000 $
b1000 )
1'
0&
#9450000
1%
#9500000
0%
b100 $
b100 )
#9550000
1%
#9600000
0%
b1101 $
b1101 )
1&
#9650000
1%
#9700000
0%
b110 $
b110 )
#9750000
1%
#9800000
0%
b101 $
b101 )
0'
0&
#9850000
1%
#9900000
0%
b111 $
b111 )
#9950000
1%
#10000000
0%
b1000 $
b1000 )
1&
#10050000
1!
0"
1%
#10100000
0%
b111 $
b111 )
1'
0&
#10150000
0!
1"
b1 +
b0 #
b0 *
1%
#10200000
0%
b1100 $
b1100 )
0'
#10250000
1%
#10300000
0%
1'
1&
#10350000
1%
#10400000
0%
b1101 $
b1101 )
0'
0&
#10450000
1%
#10500000
0%
b11 $
b11 )
#10550000
1%
#10600000
0%
b1010 $
b1010 )
#10650000
1%
#10700000
0%
b1001 $
b1001 )
1&
#10750000
0-
1%
#10800000
0%
b0 $
b0 )
#10850000
b0 ,
1-
1%
#10900000
0%
b1101 $
b1101 )
0&
#10950000
1%
#11000000
0%
b1000 $
b1000 )
#11050000
1%
#11100000
0%
b1111 $
b1111 )
1'
#11150000
1%
#11200000
0%
b1 $
b1 )
0'
1&
#11250000
1!
0"
1%
#11300000
0%
b110 $
b110 )
1'
#11350000
1%
#11400000
0%
b101 $
b101 )
0&
#11450000
0!
1"
b10 +
b1 #
b1 *
1%
#11500000
0%
1&
#11550000
1%
#11600000
0%
b11 $
b11 )
0&
#11650000
1%
#11700000
0%
b1110 $
b1110 )
0'
#11750000
1%
#11800000
0%
b1 $
b1 )
1'
#11850000
1%
#11900000
0%
b1111 $
b1111 )
0'
#11950000
1%
#12000000
0%
b1101 $
b1101 )
#12050000
1%
#12100000
0%
b1001 $
b1001 )
#12150000
1%
#12200000
0%
b11 $
b11 )
#12250000
1%
#12300000
0%
b110 $
b110 )
1'
1&
#12350000
1%
#12400000
0%
b1001 $
b1001 )
0'
0&
#12450000
1%
#12500000
0%
b1111 $
b1111 )
#12550000
1%
#12600000
0%
b10 $
b10 )
#12650000
1%
#12700000
0%
b100 $
b100 )
1'
#12750000
1%
#12800000
0%
b1001 $
b1001 )
0'
#12850000
1%
#12900000
0%
b1011 $
b1011 )
1&
#12950000
0-
1%
#13000000
0%
b1001 $
b1001 )
1'
#13050000
1%
#13100000
0%
b1111 $
b1111 )
0&
#13150000
1%
#13200000
0%
b1110 $
b1110 )
0'
1&
#13250000
b1 ,
1-
1%
#13300000
0%
b1000 $
b1000 )
#13350000
1!
0"
1%
#13400000
0%
b10 $
b10 )
1'
#13450000
1%
#13500000
0%
b1100 $
b1100 )
0&
#13550000
0!
1"
b11 +
1%
#13600000
0%
b110 $
b110 )
#13650000
1%
#13700000
0%
b1000 $
b1000 )
1&
#13750000
1%
#13800000
0%
b1011 $
b1011 )
0'
#13850000
0-
1%
#13900000
0%
b11 $
b11 )
0&
#13950000
1%
#14000000
0%
b1000 $
b1000 )
#14050000
1%
#14100000
0%
b1 $
b1 )
1'
1&
#14150000
1%
#14200000
0%
b1000 $
b1000 )
#14250000
1%
#14300000
0%
b1111 $
b1111 )
#14350000
1%
#14400000
0%
b110 $
b110 )
0'
0&
#14450000
1%
#14500000
0%
#14550000
1%
#14600000
0%
b1101 $
b1101 )
1'
1&
