DigitalCircuit/状态机基础/homework/fsm_homework.v
`timescale 1ns/1ps

module fsm(a,b,out,reset);

input a,b,reset;
output out;
reg [3:0]state,nextstate;
reg clk,outreg;
//There are 6 status in total.
parameter
S0=3'd0,
S1=3'd1,
S2=3'd2,
S3=3'd3,
S4=3'd4,
S5=3'd5,
S6=3'd6;


assign out=outreg;

initial
begin
  clk=0;
  state=S0;
  nextstate=S0;
  outreg=0;
end

always #50 clk=~clk;

always@(nextstate or reset)
    if(!reset)
    state<=S0;
    else
    state<=nextstate;


always@(posedge clk or negedge reset)
begin
            nextstate=state;
            outreg=0;
            case(state)
            S0:
            begin
                if(a==1 && b==1)
                nextstate=S1;
                else
                if(a==0 && b==0)
                nextstate=S5;
                else
                boom();
            end
            S1:
            begin
                if(a==1 && b==0)
                nextstate=S4;
                else
                if(a==0 && b==1)
                nextstate=S3;
                else
                boom();
            end
            S2:
            begin
                if(a==0 && b==0)
                nextstate=S1;
                else
                if(a==1 && b==0)
                nextstate=S5;
                else
                boom();
            end
            S3:
            begin
                if(a==0 && b==0)
                nextstate=S2;
                else
                if(a==1 && b==0)
                nextstate=S4;
                else
                boom();
            end
            S4:
            begin
                if(a==0 && b==1)
                nextstate=S5;
                else
                if(a==1 && b==0)
                nextstate=S3;
                else
                boom();
            end
            S5:
            begin
                if(a==0 && b==0)
                nextstate=S5;
                else
                if(a==1 && b==0)
                nextstate=S0;
                else
                boom();
            end
            S6:
                boom();
            default:
                boom();
            endcase
end

// always@(posedge clk or negedge reset)
// begin
// case(state):
// S0: 
// S1:
// S2:
// S3:
// S4:
// S5:
// S6:
// default:
// endcase
// end

task boom();
begin
$display("Undefined input or behavior!");
fsm.outreg=1;
end
endtask

endmodule

DigitalCircuit/状态机基础/homework/test_homework.v
`timescale 1ns/1ps

module tester;
reg a,b,reset;
reg clk;
reg rand;
wire out;

parameter
S0=3'd0,
S1=3'd1,
S2=3'd2,
S3=3'd3,
S4=3'd4,
S5=3'd5,
S6=3'd6;


fsm fsm_instance(a,b,out,reset);

initial
begin
$dumpfile("out.vcd");
$dumpvars(0,tester);
reset=1;
$monitor("state:",fsm_instance.state," statenext:",fsm_instance.nextstate," a:",a," b:",b);
$monitoron;
clk=0;
rand=0;
test(1,1,S0);
test(1,0,S1);
test(1,0,S4);
test(0,0,S3);
test(0,0,S2);
test(0,1,S1);
test(1,0,S3);
test(0,1,S4);
test(0,0,S5);
test(1,0,S5);
test(0,0,S0);
test(1,0,S5);
test(1,1,S0);
test(0,1,S1);
test(0,0,S3);
test(1,0,S2);
test(0,0,S5);
$monitoroff;
#1000;
rand=1;
$display("Start robust test!");
$display("------------------------------------------------");
$monitoron;
#10000;
$finish;
end

always # 50 clk=~clk;

always@(posedge clk)
if(rand)
begin
    a={$random}%2;
    b={$random}%2;
end

task test(ain,bin,current_state);
integer ain,bin;
integer current_state;

begin
tester.a=ain;
tester.b=bin;
$display("Current fsm_instance.state:%d\nRight state:%d",fsm_instance.state,current_state);
if(current_state!=fsm_instance.state)
$display("Fsm went to the wrong state!!!!!!!!!!!!!!!!!!!!!!!!!!!!!!!!!!");
#100;
end
endtask

// task forced_test(ain,bin,current_state,next_state);

// integer
// ain,
// bin;
// reg current_state,next_state;

// begin
// test.a=ain;
// test.b=bin;
// fsm_instance.state=current_state;
// #101;
// if(fsm.state!=next_state)
// $display("Fsm went to the wrong state!\n");
// #99;
// end
// endtask

endmodule

DigitalCircuit/状态机基础/homework/out.vcd
$date
	Thu Nov 02 17:28:26 2017
$end
$version
	Icarus Verilog
$end
$timescale
	1ps
$end
$scope module tester $end
$var wire 1 ! out $end
$var reg 1 " a $end
$var reg 1 # b $end
$var reg 1 $ clk $end
$var reg 1 % rand $end
$var reg 1 & reset $end
$scope module fsm_instance $end
$var wire 1 " a $end
$var wire 1 # b $end
$var wire 1 ! out $end
$var wire 1 & reset $end
$var reg 1 ' clk $end
$var reg 4 ( nextstate [3:0] $end
$var reg 1 ) outreg $end
$var reg 4 * state [3:0] $end
$scope task boom $end
$upscope $end
$upscope $end
$scope task test $end
$var integer 32 + ain [31:0] $end
$var integer 32 , bin [31:0] $end
$var integer 32 - current_state [31:0] $end
$upscope $end
$upscope $end
$enddefinitions $end
#0
$dumpvars
b0 -
b1 ,
b1 +
b0 *
0)
b0 (
0'
1&
0%
0$
1#
1"
0!
$end
#50000
b1 *
b1 (
1$
1'
#100000
0$
0'
0#
b1 -
b0 ,
#150000
b100 *
b100 (
1$
1'
#200000
0$
0'
b100 -
#250000
b11 *
b11 (
1$
1'
#300000
0$
0'
0"
b11 -
b0 +
#350000
b10 *
b10 (
1$
1'
#400000
0$
0'
b10 -
#450000
b1 *
b1 (
1$
1'
#500000
0$
0'
1#
b1 -
b1 ,
#550000
b11 *
b11 (
1$
1'
#600000
0$
0'
0#
1"
b11 -
b0 ,
b1 +
#650000
b100 *
b100 (
1$
1'
#700000
0$
0'
1#
0"
b100 -
b1 ,
b0 +
#750000
b101 *
b101 (
1$
1'
#800000
0$
0'
0#
b101 -
b0 ,
#850000
1$
1'
#900000
0$
0'
1"
b1 +
#950000
b0 *
b0 (
1$
1'
#1000000
0$
0'
0"
b0 -
b0 +
#1050000
b101 *
b101 (
1$
1'
#1100000
0$
0'
1"
b101 -
b1 +
#1150000
b0 *
b0 (
1$
1'
#1200000
0$
0'
1#
b0 -
b1 ,
#1250000
b1 *
b1 (
1$
1'
#1300000
0$
0'
0"
b1 -
b0 +
#1350000
b11 *
b11 (
1$
1'
#1400000
0$
0'
0#
b11 -
b0 ,
#1450000
b10 *
b10 (
1$
1'
#1500000
0$
0'
1"
b10 -
b1 +
#1550000
b101 *
b101 (
1$
1'
#1600000
0$
0'
0"
b101 -
b0 +
#1650000
1$
1'
#1700000
0$
0'
#1750000
1$
1'
#1800000
0$
0'
#1850000
1$
1'
#1900000
0$
0'
#1950000
1$
1'
#2000000
0$
0'
#2050000
1$
1'
#2100000
0$
0'
#2150000
1$
1'
#2200000
0$
0'
#2250000
1$
1'
#2300000
0$
0'
#2350000
1$
1'
#2400000
0$
0'
#2450000
1$
1'
#2500000
0$
0'
#2550000
1$
1'
#2600000
0$
0'
#2650000
1$
1'
#2700000
0$
0'
1%
#2750000
1#
1$
1'
#2800000
0$
0'
#2850000
1"
1!
1)
1$
1'
#2900000
0$
0'
#2950000
1!
1)
1$
1'
#3000000
0$
0'
#3050000
0#
1!
1)
1$
1'
#3100000
0$
0'
#3150000
b0 *
1#
b0 (
0!
0)
1$
1'
#3200000
0$
0'
#3250000
b1 *
0"
b1 (
1$
1'
#3300000
0$
0'
#3350000
b11 *
0#
1"
b11 (
1$
1'
#3400000
0$
0'
#3450000
b100 *
b100 (
1$
1'
#3500000
0$
0'
#3550000
b11 *
b11 (
1$
1'
#3600000
0$
0'
#3650000
b100 *
1#
b100 (
1$
1'
#3700000
0$
0'
#3750000
0"
1!
1)
1$
1'
#3800000
0$
0'
#3850000
b101 *
0#
b101 (
0!
0)
1$
1'
#3900000
0$
0'
#3950000
1#
1$
1'
#4000000
0$
0'
#4050000
1!
1)
1$
1'
#4100000
0$
0'
#4150000
1"
1!
1)
1$
1'
#4200000
0$
0'
#4250000
0#
1!
1)
1$
1'
#4300000
0$
0'
#4350000
b0 *
0"
b0 (
0!
0)
1$
1'
#4400000
0$
0'
#4450000
b101 *
1#
b101 (
1$
1'
#4500000
0$
0'
#4550000
1!
1)
1$
1'
#4600000
0$
0'
#4650000
1"
1!
1)
1$
1'
#4700000
0$
0'
#4750000
1!
1)
1$
1'
#4800000
0$
0'
#4850000
0#
0"
1!
1)
1$
1'
#4900000
0$
0'
#4950000
1#
1"
0!
0)
1$
1'
#5000000
0$
0'
#5050000
0#
1!
1)
1$
1'
#5100000
0$
0'
#5150000
b0 *
0"
b0 (
0!
0)
1$
1'
#5200000
0$
0'
#5250000
b101 *
b101 (
1$
1'
#5300000
0$
0'
#5350000
1"
1$
1'
#5400000
0$
0'
#5450000
b0 *
1#
0"
b0 (
1$
1'
#5500000
0$
0'
#5550000
0#
1"
1!
1)
1$
1'
#5600000
0$
0'
#5650000
0"
1!
1)
1$
1'
#5700000
0$
0'
#5750000
b101 *
b101 (
0!
0)
1$
1'
#5800000
0$
0'
#5850000
1#
1"
1$
1'
#5900000
0$
0'
#5950000
1!
1)
1$
1'
#6000000
0$
0'
#6050000
0#
1!
1)
1$
1'
#6100000
0$
0'
#6150000
b0 *
1#
0"
b0 (
0!
0)
1$
1'
#6200000
0$
0'
#6250000
1"
1!
1)
1$
1'
#6300000
0$
0'
#6350000
b1 *
0#
0"
b1 (
0!
0)
1$
1'
#6400000
0$
0'
#6450000
1#
1"
1!
1)
1$
1'
#6500000
0$
0'
#6550000
0"
1!
1)
1$
1'
#6600000
0$
0'
#6650000
b11 *
0#
1"
b11 (
0!
0)
1$
1'
#6700000
0$
0'
#6750000
b100 *
1#
b100 (
1$
1'
#6800000
0$
0'
#6850000
0#
1!
1)
1$
1'
#6900000
0$
0'
#6950000
b11 *
1#
b11 (
0!
0)
1$
1'
#7000000
0$
0'
#7050000
0#
0"
1!
1)
1$
1'
#7100000
0$
0'
#7150000
b10 *
b10 (
0!
0)
1$
1'
#7200000
0$
0'
#7250000
b1 *
1#
1"
b1 (
1$
1'
#7300000
0$
0'
#7350000
0#
0"
1!
1)
1$
1'
#7400000
0$
0'
#7450000
1#
1"
1!
1)
1$
1'
#7500000
0$
0'
#7550000
1!
1)
1$
1'
#7600000
0$
0'
#7650000
0#
1!
1)
1$
1'
#7700000
0$
0'
#7750000
b100 *
1#
b100 (
0!
0)
1$
1'
#7800000
0$
0'
#7850000
0#
1!
1)
1$
1'
#7900000
0$
0'
#7950000
b11 *
0"
b11 (
0!
0)
1$
1'
#8000000
0$
0'
#8050000
b10 *
b10 (
1$
1'
#8100000
0$
0'
#8150000
b1 *
b1 (
1$
1'
#8200000
0$
0'
#8250000
1#
1"
1!
1)
1$
1'
#8300000
0$
0'
#8350000
1!
1)
1$
1'
#8400000
0$
0'
#8450000
0#
1!
1)
1$
1'
#8500000
0$
0'
#8550000
b100 *
1#
b100 (
0!
0)
1$
1'
#8600000
0$
0'
#8650000
0#
0"
1!
1)
1$
1'
#8700000
0$
0'
#8750000
1#
1"
1!
1)
1$
1'
#8800000
0$
0'
#8850000
0"
1!
1)
1$
1'
#8900000
0$
0'
#8950000
b101 *
1"
b101 (
0!
0)
1$
1'
#9000000
0$
0'
#9050000
0#
1!
1)
1$
1'
#9100000
0$
0'
#9150000
b0 *
0"
b0 (
0!
0)
1$
1'
#9200000
0$
0'
#9250000
b101 *
1"
b101 (
1$
1'
#9300000
0$
0'
#9350000
b0 *
0"
b0 (
1$
1'
#9400000
0$
0'
#9450000
b101 *
1#
1"
b101 (
1$
1'
#9500000
0$
0'
#9550000
0#
0"
1!
1)
1$
1'
#9600000
0$
0'
#9650000
1"
0!
0)
1$
1'
#9700000
0$
0'
#9750000
b0 *
0"
b0 (
1$
1'
#9800000
0$
0'
#9850000
b101 *
1"
b101 (
1$
1'
#9900000
0$
0'
#9950000
b0 *
1#
0"
b0 (
1$
1'
#10000000
0$
0'
#10050000
1!
1)
1$
1'
#10100000
0$
0'
#10150000
1"
1!
1)
1$
1'
#10200000
0$
0'
#10250000
b1 *
b1 (
0!
0)
1$
1'
#10300000
0$
0'
#10350000
0#
0"
1!
1)
1$
1'
#10400000
0$
0'
#10450000
1#
1!
1)
1$
1'
#10500000
0$
0'
#10550000
b11 *
0#
b11 (
0!
0)
1$
1'
#10600000
0$
0'
#10650000
b10 *
1#
1"
b10 (
1$
1'
#10700000
0$
0'
#10750000
0#
0"
1!
1)
1$
1'
#10800000
0$
0'
#10850000
b1 *
1#
b1 (
0!
0)
1$
1'
#10900000
0$
0'
#10950000
b11 *
0#
1"
b11 (
1$
1'
#11000000
0$
0'
#11050000
b100 *
0"
b100 (
1$
1'
#11100000
0$
0'
#11150000
1#
1"
1!
1)
1$
1'
#11200000
0$
0'
#11250000
0#
0"
1!
1)
1$
1'
#11300000
0$
0'
#11350000
1#
1!
1)
1$
1'
#11400000
0$
0'
#11450000
b101 *
0#
b101 (
0!
0)
1$
1'
#11500000
0$
0'
#11550000
1"
1$
1'
#11600000
0$
0'
#11650000
b0 *
0"
b0 (
1$
1'
#11700000
0$
0'
#11750000
b101 *
1"
b101 (
1$
1'
#11800000
0$
0'
#11850000
b0 *
1#
b0 (
1$
1'
#11900000
0$
0'
#11950000
b1 *
0#
0"
b1 (
1$
1'
#12000000
0$
0'
#12050000
1!
1)
1$
1'
#12100000
0$
0'
#12150000
1"
1!
1)
1$
1'
#12200000
0$
0'
#12250000
b100 *
0"
b100 (
0!
0)
1$
1'
#12300000
0$
0'
#12350000
1#
1!
1)
1$
1'
#12400000
0$
0'
#12450000
b101 *
1"
b101 (
0!
0)
1$
1'
#12500000
0$
0'
#12550000
0"
1!
1)
1$
1'
#12600000
0$
0'
#12650000
1"
1!
1)
1$
1'
