DigitalCircuit/DMA/basic/dma.v
//Huaqiang Wang (c) 2017
`timescale 1ns/1ps
`define workmode_4 0 //Uses [3:0] in inout socket
`define workmode_8 1
module FIFO(
    input clk,
    input resetn,
    input workmode,
    input input_valid, output_enable,
    input [7:0] fifo_in,
    output reg[7:0] fifo_out,
    output reg output_valid,
    output reg input_enable,
    output empty,
    output full
);
reg [7:0]ram[7:0];
reg [2:0]position;
reg writehigh;

assign empty=(position==0)&(!writehigh)&(input_enable);
assign full=(position==0)&(!writehigh)&(output_valid);

always@(posedge clk)
begin
    if(!resetn)
    begin
        fifo_out<=8'b0;
        input_enable<=1;
        output_valid<=0;
        position<=3'b0;
        writehigh<=0;
    end
    else
    begin
        if(workmode==`workmode_8)
        case({input_enable,input_valid,output_enable,output_valid})
            4'b1100://input
            begin
                ram[position]<=fifo_in;
                position<=position+1;
                if(position==7)
                begin 
                    input_enable<=0;
                    output_valid<=1;
                end
            end
            4'b0011://output
            begin
                fifo_out<=ram[position];
                position<=position+1;
                if(position==7)
                begin 
                    input_enable<=1;
                    output_valid<=0;
                end
            end    
            default:
            ;
        endcase

        if(workmode==`workmode_4)
        case({input_enable,input_valid,output_enable,output_valid})
            4'b1100://input
            begin
                if(writehigh)
                begin
                    ram[position][7:4]<=fifo_in;
                    position<=position+1;
                    writehigh<=0;
                    if(position==7)
                    begin 
                        input_enable<=0;
                        output_valid<=1;
                    end
                end
                else//(!write_high)
                begin
                    ram[position][3:0]<=fifo_in;
                    writehigh<=1;
                end
            end
            4'b0011://output
            begin
                if(writehigh)
                begin
                    fifo_out[3:0]<=ram[position][7:4];
                    position<=position+1;
                    writehigh<=0;
                    if(position==7)
                    begin 
                        input_enable<=1;
                        output_valid<=0;
                    end
                end
                else//(!write_high)
                begin
                    fifo_out[3:0]<=ram[position][3:0];
                    writehigh<=1;
                end
            end   
            default:
            ;
        endcase        
    end
end

endmodule

`define mode_cpu_to_mem 1'b1
`define mode_mem_to_cpu 1'b0
`define buf1 1'b0
`define buf2 1'b1

module DMA(

input clk,
input resetn,
input mode,              //模式选择:控制DMA的工作方式:内存->CPU 或 CPU->内存

input dma_to_mem_enable, //MEM是否准备好接收数据。
input mem_to_dma_valid, //MEM中传入的数据是否有效。
input dma_to_cpu_enable, //CPU是否准备好接收数据。
input cpu_to_dma_valid, //CPU传入的数据是否有效。

input [3:0] mem_data_out, //内存信号输出
input [7:0] cpu_data_out,  //中央处理器信号输出

output dma_to_mem_valid, //向MEM传出的数据是否有效
output mem_to_dma_enable, //DMA准备好自MEM接收数据
output cpu_to_dma_enable, //DMA准备好自CPU接收数据
output dma_to_cpu_valid, //向CPU传出的数据是否有效

output [3:0] mem_data_in, //内存信号输入
output [7:0] cpu_data_in  //中央处理器信号输入
);

reg buf1_mode;
reg buf2_mode;

reg input_buf;

FIFO buf1(    
    .clk(clk),
    .resetn(resetn),
    .workmode(buf1_mode)
);

FIFO buf2(
    .clk(clk),
    .resetn(resetn),
    .workmode(buf2_mode)
);

assign dma_to_mem_valid=(mode==`mode_cpu_to_mem)&((~input_buf==`buf1)?buf1.output_valid:buf2.output_valid); 
assign mem_to_dma_enable=(mode==`mode_mem_to_cpu)&((input_buf==`buf1)?buf1.input_enable:buf2.input_enable);
assign cpu_to_dma_enable=(mode==`mode_cpu_to_mem)&((input_buf==`buf1)?buf1.input_enable:buf2.input_enable);
assign dma_to_cpu_valid=(mode==`mode_mem_to_cpu)&((~input_buf==`buf1)?buf1.output_valid:buf2.output_valid); 
assign mem_data_in=(!input_buf==`buf1)?buf1.fifo_out[3:0]:buf2.fifo_out[3:0];
assign cpu_data_in=(!input_buf==`buf1)?buf1.fifo_out:buf2.fifo_out;

// assign dma_to_mem_enable=(!input_buf==`buf1)?buf1.output_enable:buf2.output_enable;
// assign mem_to_dma_valid=(input_buf==`buf1)?buf1.input_valid:buf2.input_valid;
// assign dma_to_cpu_enable=(!input_buf==`buf1)?buf1.output_enable:buf2.output_enable;
// assign cpu_to_dma_valid=(input_buf==`buf1)?buf1.input_valid:buf2.input_valid;
assign buf1.output_enable=((mode==`mode_cpu_to_mem)?dma_to_mem_enable:dma_to_cpu_enable)&(!input_buf==`buf1);
assign buf2.output_enable=((mode==`mode_cpu_to_mem)?dma_to_mem_enable:dma_to_cpu_enable)&(!input_buf==`buf2);
assign buf1.input_valid=((mode==`mode_cpu_to_mem)?cpu_to_dma_valid:mem_to_dma_valid)&(input_buf==`buf1);
assign buf2.input_valid=((mode==`mode_cpu_to_mem)?cpu_to_dma_valid:mem_to_dma_valid)&(input_buf==`buf2);

// assign mem_data_out[3:0]=(input_buf==`buf1)?buf1.fifo_in[3:0]:buf2.fifo_in[3:0];
// assign cpu_data_out[7:0]=(input_buf==`buf1)?buf1.fifo_in:buf2.fifo_in;
assign buf1.fifo_in=((mode==`mode_cpu_to_mem)?cpu_data_out:{4'b0000,mem_data_out});
assign buf2.fifo_in=((mode==`mode_mem_to_cpu)?cpu_data_out:{4'b0000,mem_data_out});

// P-code
// always@(*)
// if(mode==`mode_mem_to_cpu)
// begin
//     if(input_buf==`buf1)
//     begin
//         mem_to_dma_enable=buf1.input_enable;
//         buf1.input_valid=mem_to_dma_valid;
//         dma_to_cpu_valid=buf2.output_valid;
//         buf2.output_enable=dma_to_cpu_enable;
//         buf1.fifo_in=mem_data_out;
//         cpu_data_in=buf2.fifo_out;
//     end
//     else//(input_buf==`buf2)
//     begin
//         mem_to_dma_enable=buf2.input_enable;
//         buf2.input_valid=mem_to_dma_valid;
//         dma_to_cpu_valid=buf1.output_valid;
//         buf1.output_enable=dma_to_cpu_enable;
//         buf2.fifo_in=mem_data_out;
//         cpu_data_in=buf1.fifo_out;
//     end
// end
// else//(mode==`mode_cpu_to_mem)
// begin
//     if(input_buf==`buf1)
//     begin
//         cpu_to_dma_enable=buf1.input_enable;
//         buf1.input_valid=cpu_to_dma_valid;
//         dma_to_mem_valid=buf2.output_valid;
//         buf2.output_enable=dma_to_mem_enable;
//         buf1.fifo_in=cpu_data_out;
//         mem_data_in=buf2.fifo_out;
//     end
//     else//(input_buf==`buf2)
//     begin
//         cpu_to_dma_enable=buf2.input_enable;
//         buf2.input_valid=cpu_to_dma_valid;
//         dma_to_mem_valid=buf1.output_valid;
//         buf1.output_enable=dma_to_mem_enable;
//         buf2.fifo_in=cpu_data_out;
//         mem_data_in=buf1.fifo_out;
//     end
// end

always@(posedge clk)
begin
    if(!resetn)
    begin
        input_buf=`buf1;
        if(mode==`mode_cpu_to_mem)
        begin
            // workmode_4
            buf1_mode<=`workmode_8;
            buf2_mode<=`workmode_4;
        end
        else//(mode==`mode_mem_to_cpu)
        begin
            buf1_mode<=`workmode_4;
            buf2_mode<=`workmode_8;
            
        end
    end
end

always@(*)
begin
    if(buf1.full&buf2.empty)
        begin 
            input_buf<=`buf2;
            if(mode==`mode_cpu_to_mem)
            begin
                buf2_mode<=`workmode_8;
                buf1_mode<=`workmode_4;
            end
            else//(mode==`mode_mem_to_cpu)
            begin
                buf2_mode<=`workmode_4;
                buf1_mode<=`workmode_8;
            end
        end
    if(buf2.full&buf1.empty)
        begin
            input_buf<=`buf1;
            if(mode==`mode_cpu_to_mem)
            begin
                buf1_mode<=`workmode_8;
                buf2_mode<=`workmode_4;
            end
            else//(mode==`mode_mem_to_cpu)
            begin
                buf1_mode<=`workmode_4;
                buf2_mode<=`workmode_8;
            end
        end
end

endmodule

DigitalCircuit/DMA/testbench.v
`define MODE 1
`timescale 1ns/1ps
// parameter mode_cpu_to_mem 1'b1;
// parameter mode_mem_to_cpu 1'b0;

module CPU(
input clk,

input cpu_to_dma_enable, //DMA准备好自CPU接收数据
input dma_to_cpu_valid, //向CPU传出的数据是否有效
input [7:0] cpu_in_socket,

output reg dma_to_cpu_enable, //CPU是否准备好接收数据。
output reg cpu_to_dma_valid, //CPU传入的数据是否有效。
output reg [7:0] cpu_out_socket
);

always@ (posedge clk)
begin
    
    //give out random status and data.
    dma_to_cpu_enable=$random%2;
    cpu_to_dma_valid=$random%2;
    cpu_out_socket=$random%'b100000000;

    if(cpu_to_dma_valid&cpu_to_dma_enable)
    begin
        $display("cpu->dma: cpu gived %d\n",cpu_out_socket);
    end

    if(dma_to_cpu_enable&dma_to_cpu_valid)
    begin
        $display("dma->cpu: cpu received %d\n",cpu_in_socket);
    end
end

endmodule

module MEM(
input clk,

input mem_to_dma_enable, //DMA准备好自MEM接收数据
input dma_to_mem_valid, //向MEM传出的数据是否有效
input [3:0] mem_in_socket,

output reg dma_to_mem_enable, //MEM是否准备好接收数据。
output reg mem_to_dma_valid, //MEM传入的数据是否有效。
output reg [3:0] mem_out_socket

);

always@ (posedge clk)
begin
    
    //give out random status and data.
    dma_to_mem_enable=$random%2;
    mem_to_dma_valid=$random%2;
    mem_out_socket=$random%'b10000;

    if(mem_to_dma_valid&mem_to_dma_enable)
    begin
        $display("mem->dma: mem gived %d\n",mem_out_socket);
    end

    if(dma_to_mem_enable&dma_to_mem_valid)
    begin
        $display("dma->mem: mem received %d\n",mem_in_socket);
    end
end

endmodule

module TEST();
reg clk;
reg resetn;
reg mode;

wire mem_to_dma_valid;
wire mem_to_dma_enable;
wire dma_to_mem_enable;
wire dma_to_mem_valid;
wire cpu_to_dma_valid;
wire cpu_to_dma_enable;
wire dma_to_cpu_enable;
wire dma_to_cpu_valid;
wire [3:0]mem_in_wire;
wire [3:0]mem_out_wire;
wire [7:0]cpu_in_wire;
wire [7:0]cpu_out_wire;

MEM memins(
    .clk(clk),
    .mem_to_dma_enable(mem_to_dma_enable),
    .mem_to_dma_valid(mem_to_dma_valid),
    .dma_to_mem_enable(dma_to_mem_enable),
    .dma_to_mem_valid(dma_to_mem_valid),
    .mem_in_socket(mem_in_wire),
    .mem_out_socket(mem_out_wire)
);

CPU cpuins(
    .clk(clk),
    .cpu_to_dma_enable(cpu_to_dma_enable),
    .cpu_to_dma_valid(cpu_to_dma_valid),
    .dma_to_cpu_enable(dma_to_cpu_enable),
    .dma_to_cpu_valid(dma_to_cpu_valid),
    .cpu_in_socket(cpu_in_wire),
    .cpu_out_socket(cpu_out_wire)
);

DMA dmains(
    .clk(clk),
    .resetn(resetn),
    .mode(mode),

    .dma_to_mem_enable(dma_to_mem_enable) , //MEM是否准备好接收数据。
    .mem_to_dma_valid(mem_to_dma_valid), //MEM中传入的数据是否有效。
    .dma_to_cpu_enable(dma_to_cpu_enable), //CPU是否准备好接收数据。
    .cpu_to_dma_valid(cpu_to_dma_valid),//CPU传入的数据是否有效。

    .mem_data_out(mem_out_wire),
    .cpu_data_out(cpu_out_wire),

    .dma_to_mem_valid(dma_to_mem_valid), //向MEM传出的数据是否有效
    .mem_to_dma_enable(mem_to_dma_enable), //DMA准备好自MEM接收数据
    .cpu_to_dma_enable(cpu_to_dma_enable), //DMA准备好自CPU接收数据
    .dma_to_cpu_valid(dma_to_mem_valid), //向CPU传出的数据是否有效

    .mem_data_in(mem_in_wire),
    .cpu_data_in(cpu_in_wire)

);


initial
begin
    $dumpfile("out.vcd");
    $dumpvars(0,TEST);
    $display("Start test.");
    clk=0;
    resetn=0;
    mode=`MODE;
    #100
    resetn=1;
   #10000
   $finish;
end

always@(posedge clk)
begin
end

always #50
begin
    clk=~clk;
end

endmodule

DigitalCircuit/DMA/basic/out.vcd
$date
	Sat Dec 23 18:27:42 2017
$end
$version
	Icarus Verilog
$end
$timescale
	1ps
$end
$scope module TEST $end
$var wire 1 ! dma_to_cpu_valid $end
$var wire 1 " dma_to_mem_valid $end
$var wire 1 # mem_to_dma_valid $end
$var wire 1 $ mem_to_dma_enable $end
$var wire 4 % mem_out_wire [3:0] $end
$var wire 4 & mem_in_wire [3:0] $end
$var wire 1 ' dma_to_mem_enable $end
$var wire 1 ( dma_to_cpu_enable $end
$var wire 1 ) cpu_to_dma_valid $end
$var wire 1 * cpu_to_dma_enable $end
$var wire 8 + cpu_out_wire [7:0] $end
$var wire 8 , cpu_in_wire [7:0] $end
$var reg 1 - clk $end
$var reg 1 . mode $end
$var reg 1 / resetn $end
$scope module cpuins $end
$var wire 1 - clk $end
$var wire 1 ! dma_to_cpu_valid $end
$var wire 1 * cpu_to_dma_enable $end
$var wire 8 0 cpu_in_socket [7:0] $end
$var reg 8 1 cpu_out_socket [7:0] $end
$var reg 1 ) cpu_to_dma_valid $end
$var reg 1 ( dma_to_cpu_enable $end
$upscope $end
$scope module dmains $end
$var wire 1 - clk $end
$var wire 8 2 cpu_data_out [7:0] $end
$var wire 1 ) cpu_to_dma_valid $end
$var wire 1 ( dma_to_cpu_enable $end
$var wire 1 " dma_to_cpu_valid $end
$var wire 1 " dma_to_mem_valid $end
$var wire 1 . mode $end
$var wire 1 / resetn $end
$var wire 1 # mem_to_dma_valid $end
$var wire 1 $ mem_to_dma_enable $end
$var wire 4 3 mem_data_out [3:0] $end
$var wire 4 4 mem_data_in [3:0] $end
$var wire 1 ' dma_to_mem_enable $end
$var wire 1 * cpu_to_dma_enable $end
$var wire 8 5 cpu_data_in [7:0] $end
$var reg 1 6 buf1_mode $end
$var reg 1 7 buf2_mode $end
$var reg 1 8 input_buf $end
$scope module buf1 $end
$var wire 1 - clk $end
$var wire 1 9 empty $end
$var wire 8 : fifo_in [7:0] $end
$var wire 1 ; full $end
$var wire 1 < input_valid $end
$var wire 1 = output_enable $end
$var wire 1 / resetn $end
$var wire 1 6 workmode $end
$var reg 8 > fifo_out [7:0] $end
$var reg 1 ? input_enable $end
$var reg 1 @ output_valid $end
$var reg 3 A position [2:0] $end
$var reg 1 B writehigh $end
$upscope $end
$scope module buf2 $end
$var wire 1 - clk $end
$var wire 1 C empty $end
$var wire 8 D fifo_in [7:0] $end
$var wire 1 E full $end
$var wire 1 F input_valid $end
$var wire 1 G output_enable $end
$var wire 1 / resetn $end
$var wire 1 7 workmode $end
$var reg 8 H fifo_out [7:0] $end
$var reg 1 I input_enable $end
$var reg 1 J output_valid $end
$var reg 3 K position [2:0] $end
$var reg 1 L writehigh $end
$upscope $end
$upscope $end
$scope module memins $end
$var wire 1 - clk $end
$var wire 1 " dma_to_mem_valid $end
$var wire 4 M mem_in_socket [3:0] $end
$var wire 1 $ mem_to_dma_enable $end
$var reg 1 ' dma_to_mem_enable $end
$var reg 4 N mem_out_socket [3:0] $end
$var reg 1 # mem_to_dma_valid $end
$upscope $end
$upscope $end
$enddefinitions $end
#0
$dumpvars
bx N
bx M
xL
bx K
xJ
xI
bx H
xG
xF
xE
b0xxxx D
xC
xB
bx A
x@
x?
bx >
x=
x<
x;
bx :
x9
x8
x7
x6
bx 5
bx 4
bx 3
bx 2
bx 1
bx 0
0/
1.
0-
bx ,
bx +
x*
x)
x(
x'
bx &
bx %
x$
x#
x"
z!
$end
#50000
19
1C
b0 &
b0 4
b0 M
0;
1*
1$
0E
0"
b0 ,
b0 0
b0 5
0B
b0 A
0@
1?
b0 >
0L
b0 K
0J
1I
b0 H
07
16
0=
1G
0F
1<
b1101 D
b1001 :
b1101 %
b1101 3
b1101 N
1#
1'
b1001 +
b1001 1
b1001 2
1)
0(
08
1-
#100000
0-
1/
#150000
09
b1 A
0<
b111101 :
b1 D
b111101 +
b111101 1
b111101 2
0)
1(
b1 %
b1 3
b1 N
0#
1-
#200000
0-
#250000
0G
b1010 D
b11111001 :
b1010 %
b1010 3
b1010 N
1#
0'
b11111001 +
b11111001 1
b11111001 2
1-
#300000
0-
#350000
1G
b11001110 :
b10 D
b11001110 +
b11001110 1
b11001110 2
b10 %
b10 3
b10 N
1'
1-
#400000
0-
#450000
1<
b101 D
b1011100 :
b101 %
b101 3
b101 N
b1011100 +
b1011100 1
b1011100 2
1)
0(
1-
#500000
0-
#550000
b10 A
0<
b10011101 :
b0 D
b10011101 +
b10011101 1
b10011101 2
0)
b0 %
b0 3
b0 N
0#
1-
#600000
0-
#650000
1<
b101 D
b1101 :
b101 %
b101 3
b101 N
1#
b1101 +
b1101 1
b1101 2
1)
1-
#700000
0-
#750000
b11 A
0G
b1010 :
b1101 D
b1010 +
b1010 1
b1010 2
1(
b1101 %
b1101 3
b1101 N
0#
0'
1-
#800000
0-
#850000
b100 A
0<
b1000 D
b11110010 :
b1000 %
b1000 3
b1000 N
1#
b11110010 +
b11110010 1
b11110010 2
0)
0(
1-
#900000
0-
#950000
b10101110 :
b1011 D
b10101110 +
b10101110 1
b10101110 2
b1011 %
b1011 3
b1011 N
1-
#1000000
0-
#1050000
1G
b1111 D
b1011 :
b1111 %
b1111 3
b1111 N
1'
b1011 +
b1011 1
b1011 2
1-
#1100000
0-
#1150000
1<
b11011001 :
b1110 D
b11011001 +
b11011001 1
b11011001 2
1)
1(
b1110 %
b1110 3
b1110 N
0#
1-
#1200000
0-
#1250000
b101 A
0<
b111 D
b10011111 :
b111 %
b111 3
b111 N
b10011111 +
b10011111 1
b10011111 2
0)
0(
1-
#1300000
0-
#1350000
1<
b11010000 :
b1011 D
b11010000 +
b11010000 1
b11010000 2
1)
1(
b1011 %
b1011 3
b1011 N
1-
#1400000
0-
#1450000
b110 A
0G
b1000 D
b10010110 :
b1000 %
b1000 3
b1000 N
0'
b10010110 +
b10010110 1
b10010110 2
1-
#1500000
0-
#1550000
b111 A
1G
b111001 :
b10 D
b111001 +
b111001 1
b111001 2
0(
b10 %
b10 3
b10 N
1#
1'
1-
#1600000
0-
#1650000
1;
0*
0$
1@
0?
b0 A
0G
b1001 D
b10000101 :
b1001 %
b1001 3
b1001 N
0'
b10000101 +
b10000101 1
b10000101 2
1(
1-
#1700000
0-
#1750000
0<
1G
b10011100 :
b1000 D
b10011100 +
b10011100 1
b10011100 2
0)
0(
b1000 %
b1000 3
b1000 N
0#
1'
1-
#1800000
0-
#1850000
b11 D
b1110011 :
b11 %
b11 3
b11 N
1#
b1110011 +
b1110011 1
b1110011 2
1-
#1900000
0-
#1950000
b1011010 :
b111 D
b1011010 +
b1011010 1
b1011010 2
1(
b111 %
b111 3
b111 N
0#
1-
#2000000
0-
#2050000
1<
b1111 D
b11011010 :
b1111 %
b1111 3
b1111 N
1#
b11011010 +
b11011010 1
b11011010 2
1)
1-
#2100000
0-
#2150000
b1110 :
b0 D
b1110 +
b1110 1
b1110 2
0(
b0 %
b0 3
b0 N
0#
1-
#2200000
0-
#2250000
0<
b1110 D
b11111101 :
b1110 %
b1110 3
b1110 N
b11111101 +
b11111101 1
b11111101 2
0)
1-
#2300000
0-
#2350000
1<
b10111000 :
b110 D
b10111000 +
b10111000 1
b10111000 2
1)
b110 %
b110 3
b110 N
1-
#2400000
0-
#2450000
b1101 D
b100 :
b1101 %
b1101 3
b1101 N
1#
b100 +
b100 1
b100 2
1-
#2500000
0-
#2550000
0<
b10010101 :
b110 D
b10010101 +
b10010101 1
b10010101 2
0)
b110 %
b110 3
b110 N
1-
#2600000
0-
#2650000
b1000 D
b11110111 :
b1000 %
b1000 3
b1000 N
0#
b11110111 +
b11110111 1
b11110111 2
1-
#2700000
0-
#2750000
0G
b11100 :
b111 D
b11100 +
b11100 1
b11100 2
b111 %
b111 3
b111 N
1#
0'
1-
#2800000
0-
#2850000
1<
b1101 D
b1101 %
b1101 3
b1101 N
0#
1)
1(
1-
#2900000
0-
#2950000
0<
b11111010 :
b11 D
b11111010 +
b11111010 1
b11111010 2
0)
0(
b11 %
b11 3
b11 N
1-
#3000000
0-
#3050000
1G
b0 D
b10111001 :
b0 %
b0 3
b0 N
1'
b10111001 +
b10111001 1
b10111001 2
1(
1-
#3100000
0-
#3150000
0G
b1111000 :
b1101 D
b1111000 +
b1111000 1
b1111000 2
0(
b1101 %
b1101 3
b1101 N
0'
1-
#3200000
0-
#3250000
1G
1<
b1 D
b11001111 :
b1 %
b1 3
b1 N
1'
b11001111 +
b11001111 1
b11001111 2
1)
1-
#3300000
0-
#3350000
b110101 :
b110 D
b110101 +
b110101 1
b110101 2
b110 %
b110 3
b110 N
1#
1-
#3400000
0-
#3450000
0G
b11 D
b11000101 :
b11 %
b11 3
b11 N
0'
b11000101 +
b11000101 1
b11000101 2
1(
1-
#3500000
0-
#3550000
b10100001 :
b1110 D
b10100001 +
b10100001 1
b10100001 2
0(
b1110 %
b1110 3
b1110 N
0#
1-
#3600000
0-
#3650000
0<
b1101 D
b10011111 :
b1101 %
b1101 3
b1101 N
b10011111 +
b10011111 1
b10011111 2
0)
1-
#3700000
0-
#3750000
b10011 :
b1001 D
b10011 +
b10011 1
b10011 2
b1001 %
b1001 3
b1001 N
1-
#3800000
0-
#3850000
1<
b10110110 :
b10110110 +
b10110110 1
b10110110 2
1)
1(
1-
#3900000
0-
#3950000
0<
b11110010 :
b1111 D
b11110010 +
b11110010 1
b11110010 2
0)
0(
b1111 %
b1111 3
b1111 N
1-
#4000000
0-
#4050000
1<
b1001 D
b10000100 :
b1001 %
b1001 3
b1001 N
b10000100 +
b10000100 1
b10000100 2
1)
1-
#4100000
0-
#4150000
1G
b11001001 :
b1011 D
b11001001 +
b11001001 1
b11001001 2
1(
b1011 %
b1011 3
b1011 N
1'
1-
#4200000
0-
#4250000
b1110 D
b10001111 :
b1110 %
b1110 3
b1110 N
b10001111 +
b10001111 1
b10001111 2
0(
1-
#4300000
0-
#4350000
b11000010 :
b1000 D
b11000010 +
b11000010 1
b11000010 2
1(
b1000 %
b1000 3
b1000 N
1-
#4400000
0-
#4450000
0G
b110 D
b11101100 :
b110 %
b110 3
b110 N
1#
0'
b11101100 +
b11101100 1
b11101100 2
0(
1-
#4500000
0-
#4550000
0<
1G
b1011011 :
b1000 D
b1011011 +
b1011011 1
b1011011 2
0)
1(
b1000 %
b1000 3
b1000 N
1'
1-
#4600000
0-
#4650000
0G
b1110011 :
0#
0'
b1110011 +
b1110011 1
b1110011 2
0(
1-
#4700000
0-
#4750000
1<
1G
b11001000 :
b1 D
b11001000 +
b11001000 1
b11001000 2
1)
1(
b1 %
b1 3
b1 N
1#
1'
1-
#4800000
0-
#4850000
0G
b110 D
b11111 :
b110 %
b110 3
b110 N
0#
0'
b11111 +
b11111 1
b11111 2
1-
#4900000
0-
#4950000
b11101101 :
b11101101 +
b11101101 1
b11101101 2
1-
#5000000
0-
#5050000
1G
b111 D
b10101101 :
b111 %
b111 3
b111 N
1'
b10101101 +
b10101101 1
b10101101 2
1-
#5100000
0-
#5150000
b1010001 :
b1001 D
b1010001 +
b1010001 1
b1010001 2
b1001 %
b1001 3
b1001 N
1#
1-
#5200000
0-
#5250000
0<
b1100 D
b11111010 :
b1100 %
b1100 3
b1100 N
b11111010 +
b11111010 1
b11111010 2
0)
1-
#5300000
0-
#5350000
0G
b11110000 :
b1000 D
b11110000 +
b11110000 1
b11110000 2
b1000 %
b1000 3
b1000 N
0#
0'
1-
#5400000
0-
#5450000
b0 D
b101000 :
b0 %
b0 3
b0 N
1#
b101000 +
b101000 1
b101000 2
0(
1-
#5500000
0-
#5550000
b1100010 :
b1100010 +
b1100010 1
b1100010 2
1-
#5600000
0-
#5650000
1G
1<
b110 D
b10111 :
b110 %
b110 3
b110 N
1'
b10111 +
b10111 1
b10111 2
1)
1(
1-
#5700000
0-
#5750000
b101100 :
b1101 D
b101100 +
b101100 1
b101100 2
0(
b1101 %
b1101 3
b1101 N
1-
#5800000
0-
#5850000
0G
b1110 D
b111011 :
b1110 %
b1110 3
b1110 N
0'
b111011 +
b111011 1
b111011 2
1-
#5900000
0-
#5950000
0<
b10110100 :
b0 D
b10110100 +
b10110100 1
b10110100 2
0)
b0 %
b0 3
b0 N
1-
#6000000
0-
#6050000
1G
1<
b1101 D
b1001011 :
b1101 %
b1101 3
b1101 N
0#
1'
b1001011 +
b1001011 1
b1001011 2
1)
1(
1-
#6100000
0-
#6150000
b10110001 :
b11 D
b10110001 +
b10110001 1
b10110001 2
b11 %
b11 3
b11 N
1#
1-
#6200000
0-
#6250000
b1000 D
b11100000 :
b1000 %
b1000 3
b1000 N
0#
b11100000 +
b11100000 1
b11100000 2
0(
1-
#6300000
0-
#6350000
0<
b10010000 :
b100 D
b10010000 +
b10010000 1
b10010000 2
0)
b100 %
b100 3
b100 N
1-
#6400000
0-
#6450000
0G
b0 D
b10000100 :
b0 %
b0 3
b0 N
0'
b10000100 +
b10000100 1
b10000100 2
1(
1-
#6500000
0-
#6550000
b10100010 :
b110 D
b10100010 +
b10100010 1
b10100010 2
b110 %
b110 3
b110 N
1#
1-
#6600000
0-
#6650000
1G
b111 D
b111101 :
b111 %
b111 3
b111 N
0#
1'
b111101 +
b111101 1
b111101 2
1-
#6700000
0-
#6750000
0G
b10001100 :
b100 D
b10001100 +
b10001100 1
b10001100 2
0(
b100 %
b100 3
b100 N
1#
0'
1-
#6800000
0-
#6850000
b11 D
b10001 :
b11 %
b11 3
b11 N
b10001 +
b10001 1
b10001 2
1(
1-
#6900000
0-
#6950000
1<
b11011111 :
b100 D
b11011111 +
b11011111 1
b11011111 2
1)
b100 %
b100 3
b100 N
1-
#7000000
0-
#7050000
b1001 D
b10011101 :
b1001 %
b1001 3
b1001 N
0#
b10011101 +
b10011101 1
b10011101 2
0(
1-
#7100000
0-
#7150000
1G
b101010 :
b1100 D
b101010 +
b101010 1
b101010 2
1(
b1100 %
b1100 3
b1100 N
1'
1-
#7200000
0-
#7250000
0G
b1001 D
b111010 :
b1001 %
b1001 3
b1001 N
1#
0'
b111010 +
b111010 1
b111010 2
0(
1-
#7300000
0-
#7350000
0<
b10010111 :
b10010111 +
b10010111 1
b10010111 2
0)
0#
1-
#7400000
0-
#7450000
b10111011 :
1#
b10111011 +
b10111011 1
b10111011 2
1(
1-
#7500000
0-
#7550000
b1010001 :
b101 D
b1010001 +
b1010001 1
b1010001 2
b101 %
b101 3
b101 N
1-
#7600000
0-
#7650000
1<
b100 D
b1001010 :
b100 %
b100 3
b100 N
b1001010 +
b1001010 1
b1001010 2
1)
1-
#7700000
0-
#7750000
b10110101 :
b110 D
b10110101 +
b10110101 1
b10110101 2
0(
b110 %
b110 3
b110 N
1-
#7800000
0-
#7850000
1G
b1 D
b1110110 :
b1 %
b1 3
b1 N
1'
b1110110 +
b1110110 1
b1110110 2
1-
#7900000
0-
#7950000
0<
b10101111 :
b10 D
b10101111 +
b10101111 1
b10101111 2
0)
1(
b10 %
b10 3
b10 N
0#
1-
#8000000
0-
#8050000
0G
1<
b1111 D
b11101001 :
b1111 %
b1111 3
b1111 N
0'
b11101001 +
b11101001 1
b11101001 2
1)
0(
1-
#8100000
0-
#8150000
1G
b101000 :
b1110 D
b101000 +
b101000 1
b101000 2
b1110 %
b1110 3
b1110 N
1#
1'
1-
#8200000
0-
#8250000
b1 D
b11100001 :
b1 %
b1 3
b1 N
0#
b11100001 +
b11100001 1
b11100001 2
1-
#8300000
0-
#8350000
b11110001 :
b0 D
b11110001 +
b11110001 1
b11110001 2
b0 %
b0 3
b0 N
1-
#8400000
0-
#8450000
0G
0<
b1111 D
b11100010 :
b1111 %
b1111 3
b1111 N
1#
0'
b11100010 +
b11100010 1
b11100010 2
0)
1(
1-
#8500000
0-
#8550000
1<
1G
b10011 :
b1010 D
b10011 +
b10011 1
b10011 2
1)
b1010 %
b1010 3
b1010 N
1'
1-
#8600000
0-
#8650000
b1 D
b10110111 :
b1 %
b1 3
b1 N
0#
b10110111 +
b10110111 1
b10110111 2
1-
#8700000
0-
#8750000
0G
b11100101 :
b1010 D
b11100101 +
b11100101 1
b11100101 2
b1010 %
b1010 3
b1010 N
0'
1-
#8800000
0-
#8850000
1G
b1101 D
b1000001 :
b1101 %
b1101 3
b1101 N
1#
1'
b1000001 +
b1000001 1
b1000001 2
1-
#8900000
0-
#8950000
0<
0G
b11011100 :
b10 D
b11011100 +
b11011100 1
b11011100 2
0)
b10 %
b10 3
b10 N
0#
0'
1-
#9000000
0-
#9050000
1<
b1100 D
b100101 :
b1100 %
b1100 3
b1100 N
b100101 +
b100101 1
b100101 2
1)
0(
1-
#9100000
0-
#9150000
0<
1G
b1110011 :
b1000 D
b1110011 +
b1110011 1
b1110011 2
0)
1(
b1000 %
b1000 3
b1000 N
1#
1'
1-
#9200000
0-
#9250000
b11 D
b11010100 :
b11 %
b11 3
b11 N
b11010100 +
b11010100 1
b11010100 2
0(
1-
#9300000
0-
#9350000
0G
b10101 :
b1100 D
b10101 +
b10101 1
b10101 2
1(
b1100 %
b1100 3
b1100 N
0'
1-
#9400000
0-
#9450000
b1101 D
b10 :
b1101 %
b1101 3
b1101 N
0#
b10 +
b10 1
b10 2
1-
#9500000
0-
#9550000
1G
b1111011 :
b0 D
b1111011 +
b1111011 1
b1111011 2
b0 %
b0 3
b0 N
1'
1-
#9600000
0-
#9650000
0G
1<
b1001 D
b1101 :
b1001 %
b1001 3
b1001 N
1#
0'
b1101 +
b1101 1
b1101 2
1)
0(
1-
#9700000
0-
#9750000
b1001101 :
b0 D
b1001101 +
b1001101 1
b1001101 2
b0 %
b0 3
b0 N
0#
1-
#9800000
0-
#9850000
b1100 D
b1011101 :
b1100 %
b1100 3
b1100 N
b1011101 +
b1011101 1
b1011101 2
1(
1-
#9900000
0-
#9950000
b10010011 :
b1010 D
b10010011 +
b10010011 1
b10010011 2
0(
b1010 %
b1010 3
b1010 N
1-
#10000000
0-
#10050000
1G
b110 D
b1000101 :
b110 %
b110 3
b110 N
1#
1'
b1000101 +
b1000101 1
b1000101 2
1(
1-
