DigitalCircuit/状态机基础/fsm.v
`timescale 1ns/1ps

module fsm(in1, out1,reset);

input 
in1,
reset;

output out1;

reg [1:0]
current_state,
next_state;

reg
toout,
clk;

parameter
IDLE=2'd0,
state1 =2'd1,
state2 =2'd2,
state3 =2'd3;

assign out1=toout;

initial
begin
  clk<=0;
  current_state<=2;
  next_state<=1;
end

always #50 clk=~clk;

always@(posedge clk)
begin
    current_state<=next_state;
end

always@(current_state or posedge reset)
begin
    next_state=IDLE;
    if(reset)
    current_state=IDLE;
    else
    begin
    case(current_state)
    IDLE:
        next_state<=IDLE;
    state1:
        next_state<=state2;
    state2:
        next_state<=state3;
    state3:
        next_state<=state1;
    default:
        next_state<=state1;
    endcase
    end
end

always@(posedge clk or reset or in1)
begin
    case(next_state)
    IDLE:
        toout<=0;
    state1:
        toout<=1;
    state2:
        toout<=0;
    state3:
        toout<=1;
    default:
        toout<=0;
    endcase
end

endmodule

DigitalCircuit/状态机基础/practice/testfsm.v
`timescale 1ns/1ps
module testfsm;
reg in;
wire out;
reg reset;

fsm alpha_instance(in,out,reset);

initial
begin
in=0;
reset=0;
end

initial
begin
  $dumpfile("out.vcd");
  $dumpvars(0,testfsm);
//   $monitor("inn:",in,"out",out);
//   $monitoron;
  # 5000;
  reset=1;
  #10000;
  $finish;
end

endmodule

DigitalCircuit/状态机基础/out.vcd
$date
	Fri Oct 27 21:42:25 2017
$end
$version
	Icarus Verilog
$end
$timescale
	1ps
$end
$scope module testfsm $end
$var wire 1 ! out $end
$var reg 1 " in $end
$var reg 1 # reset $end
$scope module alpha_instance $end
$var wire 1 " in1 $end
$var wire 1 ! out1 $end
$var wire 1 # reset $end
$var reg 1 $ clk $end
$var reg 2 % current_state [1:0] $end
$var reg 2 & next_state [1:0] $end
$var reg 1 ' toout $end
$upscope $end
$upscope $end
$enddefinitions $end
#0
$dumpvars
0'
b11 &
b10 %
0$
0#
0"
0!
$end
#50000
b1 &
1!
1'
b11 %
1$
#100000
0$
#150000
b10 &
b1 %
1$
#200000
0$
#250000
b11 &
0!
0'
b10 %
1$
#300000
0$
#350000
b1 &
1!
1'
b11 %
1$
#400000
0$
#450000
b10 &
b1 %
1$
#500000
0$
#550000
b11 &
0!
0'
b10 %
1$
#600000
0$
#650000
b1 &
1!
1'
b11 %
1$
#700000
0$
#750000
b10 &
b1 %
1$
#800000
0$
#850000
b11 &
0!
0'
b10 %
1$
#900000
0$
#950000
b1 &
1!
1'
b11 %
1$
#1000000
0$
#1050000
b10 &
b1 %
1$
#1100000
0$
#1150000
b11 &
0!
0'
b10 %
1$
#1200000
0$
#1250000
b1 &
1!
1'
b11 %
1$
#1300000
0$
#1350000
b10 &
b1 %
1$
#1400000
0$
#1450000
b11 &
0!
0'
b10 %
1$
#1500000
0$
#1550000
b1 &
1!
1'
b11 %
1$
#1600000
0$
#1650000
b10 &
b1 %
1$
#1700000
0$
#1750000
b11 &
0!
0'
b10 %
1$
#1800000
0$
#1850000
b1 &
1!
1'
b11 %
1$
#1900000
0$
#1950000
b10 &
b1 %
1$
#2000000
0$
#2050000
b11 &
0!
0'
b10 %
1$
#2100000
0$
#2150000
b1 &
1!
1'
b11 %
1$
#2200000
0$
#2250000
b10 &
b1 %
1$
#2300000
0$
#2350000
b11 &
0!
0'
b10 %
1$
#2400000
0$
#2450000
b1 &
1!
1'
b11 %
1$
#2500000
0$
#2550000
b10 &
b1 %
1$
#2600000
0$
#2650000
b11 &
0!
0'
b10 %
1$
#2700000
0$
#2750000
b1 &
1!
1'
b11 %
1$
#2800000
0$
#2850000
b10 &
b1 %
1$
#2900000
0$
#2950000
b11 &
0!
0'
b10 %
1$
#3000000
0$
#3050000
b1 &
1!
1'
b11 %
1$
#3100000
0$
#3150000
b10 &
b1 %
1$
#3200000
0$
#3250000
b11 &
0!
0'
b10 %
1$
#3300000
0$
#3350000
b1 &
1!
1'
b11 %
1$
#3400000
0$
#3450000
b10 &
b1 %
1$
#3500000
0$
#3550000
b11 &
0!
0'
b10 %
1$
#3600000
0$
#3650000
b1 &
1!
1'
b11 %
1$
#3700000
0$
#3750000
b10 &
b1 %
1$
#3800000
0$
#3850000
b11 &
0!
0'
b10 %
1$
#3900000
0$
#3950000
b1 &
1!
1'
b11 %
1$
#4000000
0$
#4050000
b10 &
b1 %
1$
#4100000
0$
#4150000
b11 &
0!
0'
b10 %
1$
#4200000
0$
#4250000
b1 &
1!
1'
b11 %
1$
#4300000
0$
#4350000
b10 &
b1 %
1$
#4400000
0$
#4450000
b11 &
0!
0'
b10 %
1$
#4500000
0$
#4550000
b1 &
1!
1'
b11 %
1$
#4600000
0$
#4650000
b10 &
b1 %
1$
#4700000
0$
#4750000
b11 &
0!
0'
b10 %
1$
#4800000
0$
#4850000
b1 &
1!
1'
b11 %
1$
#4900000
0$
#4950000
b10 &
b1 %
1$
#5000000
0!
0'
b0 %
b0 &
0$
1#
